{"charts":[{"weeklyartistchart":{"artist":[{"mbid":"c3aeb863-7b26-4388-94e8-5a240f2be21b","url":"https://www.last.fm/music/Tom+Waits","name":"Tom Waits","@attr":{"rank":"1"},"playcount":"34"},{"mbid":"0743b15a-3c32-48c8-ad58-cb325350befa","url":"https://www.last.fm/music/blink-182","name":"blink-182","@attr":{"rank":"2"},"playcount":"19"},{"mbid":"aba64937-3334-4c65-90a1-4e6b9d4d7ada","url":"https://www.last.fm/music/Aesop+Rock","name":"Aesop Rock","@attr":{"rank":"3"},"playcount":"18"},{"mbid":"565ac6c2-e47d-4b5f-99f1-24afdf97903a","url":"https://www.last.fm/music/Sedimentum","name":"Sedimentum","@attr":{"rank":"4"},"playcount":"18"},{"mbid":"583352d8-936c-44fd-a74c-f43154c7aad8","url":"https://www.last.fm/music/Vertebra+Atlantis","name":"Vertebra Atlantis","@attr":{"rank":"5"},"playcount":"14"},{"mbid":"68d258b4-d6cd-4a05-9cc0-98c2e1f1993a","url":"https://www.last.fm/music/Chaotian","name":"Chaotian","@attr":{"rank":"6"},"playcount":"13"},{"mbid":"2de34daa-7256-495f-84c2-9f7459748492","url":"https://www.last.fm/music/Hooded+Menace","name":"Hooded Menace","@attr":{"rank":"7"},"playcount":"12"},{"mbid":"12a9e259-f7cb-4fca-87b1-a6c5fd38c300","url":"https://www.last.fm/music/Hot+Mulligan","name":"Hot Mulligan","@attr":{"rank":"8"},"playcount":"12"},{"mbid":"5c9dd772-a38f-4873-baa8-4b5d9dff3990","url":"https://www.last.fm/music/Spanish+Love+Songs","name":"Spanish Love Songs","@attr":{"rank":"9"},"playcount":"12"},{"mbid":"664c3e0e-42d8-48c1-b209-1efca19c0325","url":"https://www.last.fm/music/The+National","name":"The National","@attr":{"rank":"10"},"playcount":"12"},{"mbid":"7fcd488b-f3fc-40c8-a82c-c18317d72aae","url":"https://www.last.fm/music/Gutvoid","name":"Gutvoid","@attr":{"rank":"11"},"playcount":"11"},{"mbid":"a521f1a8-a949-4dcf-ab33-94596cb02787","url":"https://www.last.fm/music/Militarie+Gun","name":"Militarie Gun","@attr":{"rank":"12"},"playcount":"11"},{"mbid":"3ac482b8-1494-4071-a0e9-f192f9d2c2b0","url":"https://www.last.fm/music/Built+to+Spill","name":"Built to Spill","@attr":{"rank":"13"},"playcount":"10"},{"mbid":"6e7aea5b-de9f-4118-ae32-ddea8198864a","url":"https://www.last.fm/music/Dogleg","name":"Dogleg","@attr":{"rank":"14"},"playcount":"10"},{"mbid":"20244d07-534f-4eff-b4d4-930878889970","url":"https://www.last.fm/music/Taylor+Swift","name":"Taylor Swift","@attr":{"rank":"15"},"playcount":"9"},{"mbid":"561d854a-6a28-4aa7-8c99-323e6ce46c2a","url":"https://www.last.fm/music/Miles+Davis","name":"Miles Davis","@attr":{"rank":"16"},"playcount":"8"},{"mbid":"c16dcdae-a651-42c1-aff8-edda0f463157","url":"https://www.last.fm/music/Soft+Kill","name":"Soft Kill","@attr":{"rank":"17"},"playcount":"8"},{"mbid":"552cd2a3-ac51-464d-8222-dcdbb08a8d2d","url":"https://www.last.fm/music/Tomb+Mold","name":"Tomb Mold","@attr":{"rank":"18"},"playcount":"8"},{"mbid":"4c291959-23e9-429d-ab8d-bc8b0a8ef5e9","url":"https://www.last.fm/music/Ghastly","name":"Ghastly","@attr":{"rank":"19"},"playcount":"7"},{"mbid":"","url":"https://www.last.fm/music/Inanna","name":"Inanna","@attr":{"rank":"20"},"playcount":"7"},{"mbid":"","url":"https://www.last.fm/music/AFI","name":"AFI","@attr":{"rank":"21"},"playcount":"6"},{"mbid":"","url":"https://www.last.fm/music/home+is+where","name":"home is where","@attr":{"rank":"22"},"playcount":"6"},{"mbid":"03f9e6f0-7c7f-4fd6-a47f-f0b0425f314b","url":"https://www.last.fm/music/Mis%C3%BEyrming","name":"Misþyrming","@attr":{"rank":"23"},"playcount":"6"},{"mbid":"4ef06a0d-b8d1-42b4-aff8-06f223306cdb","url":"https://www.last.fm/music/Cloud+Rat","name":"Cloud Rat","@attr":{"rank":"24"},"playcount":"5"},{"mbid":"67d1433c-6354-4fb4-bb57-bd21c4904eed","url":"https://www.last.fm/music/Desecresy","name":"Desecresy","@attr":{"rank":"25"},"playcount":"4"},{"mbid":"4236acde-2ce2-441c-a3d4-38d55f1b5474","url":"https://www.last.fm/music/Explosions+in+the+Sky","name":"Explosions in the Sky","@attr":{"rank":"26"},"playcount":"4"},{"mbid":"61ed9c9c-79eb-4e8f-8015-bd599ac0ab49","url":"https://www.last.fm/music/Katatonia","name":"Katatonia","@attr":{"rank":"27"},"playcount":"4"},{"mbid":"f6e61750-a6b7-4d88-979b-052345cd0e4a","url":"https://www.last.fm/music/Sturgill+Simpson","name":"Sturgill Simpson","@attr":{"rank":"28"},"playcount":"4"},{"mbid":"69421e11-e4c3-4854-951b-ceab4972e38e","url":"https://www.last.fm/music/Alkaline+Trio","name":"Alkaline Trio","@attr":{"rank":"29"},"playcount":"3"},{"mbid":"f66d378e-d9f0-4c5d-a4b9-0ee1b9fb2e09","url":"https://www.last.fm/music/Anxious","name":"Anxious","@attr":{"rank":"30"},"playcount":"2"},{"mbid":"","url":"https://www.last.fm/music/Basement","name":"Basement","@attr":{"rank":"31"},"playcount":"2"},{"mbid":"","url":"https://www.last.fm/music/Nothing","name":"Nothing","@attr":{"rank":"32"},"playcount":"2"},{"mbid":"7e13cd1c-0300-4d03-bd8e-5f86dd99d74f","url":"https://www.last.fm/music/At+the+Drive-In","name":"At the Drive-In","@attr":{"rank":"33"},"playcount":"1"},{"mbid":"a5eb1b55-1a67-4b2e-bf1b-ae575cf4a5c8","url":"https://www.last.fm/music/Lykathea+Aflame","name":"Lykathea Aflame","@attr":{"rank":"34"},"playcount":"1"}],"@attr":{"from":"1699358400","user":"coryd_","to":"1699963200"}}},{"weeklyartistchart":{"artist":[{"mbid":"c3aeb863-7b26-4388-94e8-5a240f2be21b","url":"https://www.last.fm/music/Tom+Waits","name":"Tom Waits","@attr":{"rank":"1"},"playcount":"34"},{"mbid":"cd956e47-4b34-4a3d-b053-1d8dc5a36f49","url":"https://www.last.fm/music/Execration","name":"Execration","@attr":{"rank":"2"},"playcount":"30"},{"mbid":"aba64937-3334-4c65-90a1-4e6b9d4d7ada","url":"https://www.last.fm/music/Aesop+Rock","name":"Aesop Rock","@attr":{"rank":"3"},"playcount":"27"},{"mbid":"","url":"https://www.last.fm/music/Basement","name":"Basement","@attr":{"rank":"4"},"playcount":"24"},{"mbid":"0743b15a-3c32-48c8-ad58-cb325350befa","url":"https://www.last.fm/music/blink-182","name":"blink-182","@attr":{"rank":"5"},"playcount":"19"},{"mbid":"565ac6c2-e47d-4b5f-99f1-24afdf97903a","url":"https://www.last.fm/music/Sedimentum","name":"Sedimentum","@attr":{"rank":"6"},"playcount":"18"},{"mbid":"37e9d7b2-7779-41b2-b2eb-3685351caad3","url":"https://www.last.fm/music/NoMeansNo","name":"NoMeansNo","@attr":{"rank":"7"},"playcount":"15"},{"mbid":"583352d8-936c-44fd-a74c-f43154c7aad8","url":"https://www.last.fm/music/Vertebra+Atlantis","name":"Vertebra Atlantis","@attr":{"rank":"8"},"playcount":"14"},{"mbid":"69421e11-e4c3-4854-951b-ceab4972e38e","url":"https://www.last.fm/music/Alkaline+Trio","name":"Alkaline Trio","@attr":{"rank":"9"},"playcount":"13"},{"mbid":"68d258b4-d6cd-4a05-9cc0-98c2e1f1993a","url":"https://www.last.fm/music/Chaotian","name":"Chaotian","@attr":{"rank":"10"},"playcount":"13"},{"mbid":"2de34daa-7256-495f-84c2-9f7459748492","url":"https://www.last.fm/music/Hooded+Menace","name":"Hooded Menace","@attr":{"rank":"11"},"playcount":"12"},{"mbid":"12a9e259-f7cb-4fca-87b1-a6c5fd38c300","url":"https://www.last.fm/music/Hot+Mulligan","name":"Hot Mulligan","@attr":{"rank":"12"},"playcount":"12"},{"mbid":"5c9dd772-a38f-4873-baa8-4b5d9dff3990","url":"https://www.last.fm/music/Spanish+Love+Songs","name":"Spanish Love Songs","@attr":{"rank":"13"},"playcount":"12"},{"mbid":"664c3e0e-42d8-48c1-b209-1efca19c0325","url":"https://www.last.fm/music/The+National","name":"The National","@attr":{"rank":"14"},"playcount":"12"},{"mbid":"7fcd488b-f3fc-40c8-a82c-c18317d72aae","url":"https://www.last.fm/music/Gutvoid","name":"Gutvoid","@attr":{"rank":"15"},"playcount":"11"},{"mbid":"d475788f-837d-4f96-9eec-2f5e32d7d163","url":"https://www.last.fm/music/Imperial+Triumphant","name":"Imperial Triumphant","@attr":{"rank":"16"},"playcount":"11"},{"mbid":"a521f1a8-a949-4dcf-ab33-94596cb02787","url":"https://www.last.fm/music/Militarie+Gun","name":"Militarie Gun","@attr":{"rank":"17"},"playcount":"11"},{"mbid":"3ac482b8-1494-4071-a0e9-f192f9d2c2b0","url":"https://www.last.fm/music/Built+to+Spill","name":"Built to Spill","@attr":{"rank":"18"},"playcount":"10"},{"mbid":"6e7aea5b-de9f-4118-ae32-ddea8198864a","url":"https://www.last.fm/music/Dogleg","name":"Dogleg","@attr":{"rank":"19"},"playcount":"10"},{"mbid":"561d854a-6a28-4aa7-8c99-323e6ce46c2a","url":"https://www.last.fm/music/Miles+Davis","name":"Miles Davis","@attr":{"rank":"20"},"playcount":"10"},{"mbid":"5b67060c-6ec8-4ee8-9783-2207c169402d","url":"https://www.last.fm/music/Svartidau%C3%B0i","name":"Svartidauði","@attr":{"rank":"21"},"playcount":"10"},{"mbid":"bf728dfa-543c-48cd-9e7a-cb46a150a20e","url":"https://www.last.fm/music/Autophagy","name":"Autophagy","@attr":{"rank":"22"},"playcount":"9"},{"mbid":"20244d07-534f-4eff-b4d4-930878889970","url":"https://www.last.fm/music/Taylor+Swift","name":"Taylor Swift","@attr":{"rank":"23"},"playcount":"9"},{"mbid":"c16dcdae-a651-42c1-aff8-edda0f463157","url":"https://www.last.fm/music/Soft+Kill","name":"Soft Kill","@attr":{"rank":"24"},"playcount":"8"},{"mbid":"552cd2a3-ac51-464d-8222-dcdbb08a8d2d","url":"https://www.last.fm/music/Tomb+Mold","name":"Tomb Mold","@attr":{"rank":"25"},"playcount":"8"},{"mbid":"37ea73dd-a48c-4659-8b9d-5c77bd9cbd12","url":"https://www.last.fm/music/Deathspell+Omega","name":"Deathspell Omega","@attr":{"rank":"26"},"playcount":"7"},{"mbid":"4c291959-23e9-429d-ab8d-bc8b0a8ef5e9","url":"https://www.last.fm/music/Ghastly","name":"Ghastly","@attr":{"rank":"27"},"playcount":"7"},{"mbid":"","url":"https://www.last.fm/music/Inanna","name":"Inanna","@attr":{"rank":"28"},"playcount":"7"},{"mbid":"","url":"https://www.last.fm/music/AFI","name":"AFI","@attr":{"rank":"29"},"playcount":"6"},{"mbid":"","url":"https://www.last.fm/music/home+is+where","name":"home is where","@attr":{"rank":"30"},"playcount":"6"},{"mbid":"03f9e6f0-7c7f-4fd6-a47f-f0b0425f314b","url":"https://www.last.fm/music/Mis%C3%BEyrming","name":"Misþyrming","@attr":{"rank":"31"},"playcount":"6"},{"mbid":"4ef06a0d-b8d1-42b4-aff8-06f223306cdb","url":"https://www.last.fm/music/Cloud+Rat","name":"Cloud Rat","@attr":{"rank":"32"},"playcount":"5"},{"mbid":"67d1433c-6354-4fb4-bb57-bd21c4904eed","url":"https://www.last.fm/music/Desecresy","name":"Desecresy","@attr":{"rank":"33"},"playcount":"4"},{"mbid":"4236acde-2ce2-441c-a3d4-38d55f1b5474","url":"https://www.last.fm/music/Explosions+in+the+Sky","name":"Explosions in the Sky","@attr":{"rank":"34"},"playcount":"4"},{"mbid":"61ed9c9c-79eb-4e8f-8015-bd599ac0ab49","url":"https://www.last.fm/music/Katatonia","name":"Katatonia","@attr":{"rank":"35"},"playcount":"4"},{"mbid":"f6e61750-a6b7-4d88-979b-052345cd0e4a","url":"https://www.last.fm/music/Sturgill+Simpson","name":"Sturgill Simpson","@attr":{"rank":"36"},"playcount":"4"},{"mbid":"dfb1592c-3031-470e-a7f1-f5455e58c160","url":"https://www.last.fm/music/Void+Rot","name":"Void Rot","@attr":{"rank":"37"},"playcount":"3"},{"mbid":"f66d378e-d9f0-4c5d-a4b9-0ee1b9fb2e09","url":"https://www.last.fm/music/Anxious","name":"Anxious","@attr":{"rank":"38"},"playcount":"2"},{"mbid":"","url":"https://www.last.fm/music/Nothing","name":"Nothing","@attr":{"rank":"39"},"playcount":"2"},{"mbid":"7e13cd1c-0300-4d03-bd8e-5f86dd99d74f","url":"https://www.last.fm/music/At+the+Drive-In","name":"At the Drive-In","@attr":{"rank":"40"},"playcount":"1"},{"mbid":"a5eb1b55-1a67-4b2e-bf1b-ae575cf4a5c8","url":"https://www.last.fm/music/Lykathea+Aflame","name":"Lykathea Aflame","@attr":{"rank":"41"},"playcount":"1"}],"@attr":{"from":"1699531200","user":"coryd_","to":"1700136000"}}},{"weeklyartistchart":{"artist":[{"mbid":"d4ad0149-d8ae-4105-8009-0221fce9ff35","url":"https://www.last.fm/music/Minutemen","name":"Minutemen","@attr":{"rank":"1"},"playcount":"43"},{"mbid":"37e9d7b2-7779-41b2-b2eb-3685351caad3","url":"https://www.last.fm/music/NoMeansNo","name":"NoMeansNo","@attr":{"rank":"2"},"playcount":"32"},{"mbid":"c80f38a6-9980-485d-997c-5c1a9cbd0d64","url":"https://www.last.fm/music/Ryan+Adams","name":"Ryan Adams","@attr":{"rank":"3"},"playcount":"31"},{"mbid":"c837c0fa-74dd-483b-95f7-25a46f92fa88","url":"https://www.last.fm/music/Prince+Daddy+&+The+Hyena","name":"Prince Daddy & The Hyena","@attr":{"rank":"4"},"playcount":"27"},{"mbid":"233fc3f3-6de2-465c-985e-e721dbabbace","url":"https://www.last.fm/music/Fugazi","name":"Fugazi","@attr":{"rank":"5"},"playcount":"24"},{"mbid":"871f06b4-c945-49f6-9ed3-de6dc9371bba","url":"https://www.last.fm/music/Morbus+Chron","name":"Morbus Chron","@attr":{"rank":"6"},"playcount":"22"},{"mbid":"bbcc9824-31c0-4c70-a7af-d24090ea161e","url":"https://www.last.fm/music/Cock+Sparrer","name":"Cock Sparrer","@attr":{"rank":"7"},"playcount":"18"},{"mbid":"f6e61750-a6b7-4d88-979b-052345cd0e4a","url":"https://www.last.fm/music/Sturgill+Simpson","name":"Sturgill Simpson","@attr":{"rank":"8"},"playcount":"16"},{"mbid":"70923a5d-d3ba-4ef7-9064-ea5f709aa076","url":"https://www.last.fm/music/Have+a+Nice+Life","name":"Have a Nice Life","@attr":{"rank":"9"},"playcount":"13"},{"mbid":"32d2897c-4c91-46db-8161-f51d3f4f0d93","url":"https://www.last.fm/music/Drug+Church","name":"Drug Church","@attr":{"rank":"10"},"playcount":"12"},{"mbid":"e6552d1c-4f4a-4e79-9e5c-f11580e8f585","url":"https://www.last.fm/music/Faceless+Burial","name":"Faceless Burial","@attr":{"rank":"11"},"playcount":"12"},{"mbid":"e7b4c928-8c45-4ecf-9f08-da64fe5c2ddd","url":"https://www.last.fm/music/Mg%C5%82a","name":"Mgła","@attr":{"rank":"12"},"playcount":"12"},{"mbid":"","url":"https://www.last.fm/music/Pigment+Vehicle","name":"Pigment Vehicle","@attr":{"rank":"13"},"playcount":"12"},{"mbid":"cc546218-cc08-4ae9-9592-ac1596c1470d","url":"https://www.last.fm/music/Propagandhi","name":"Propagandhi","@attr":{"rank":"14"},"playcount":"12"},{"mbid":"","url":"https://www.last.fm/music/Fumes","name":"Fumes","@attr":{"rank":"15"},"playcount":"10"},{"mbid":"3165f5e0-44ff-446a-81d7-c09ec69661ae","url":"https://www.last.fm/music/PUP","name":"PUP","@attr":{"rank":"16"},"playcount":"10"},{"mbid":"79792daa-d6b8-4e6d-b743-3ccb6fd9d1a4","url":"https://www.last.fm/music/Cemetery+Dwell","name":"Cemetery Dwell","@attr":{"rank":"17"},"playcount":"9"},{"mbid":"","url":"https://www.last.fm/music/Cruciamentum","name":"Cruciamentum","@attr":{"rank":"18"},"playcount":"9"},{"mbid":"","url":"https://www.last.fm/music/Altars","name":"Altars","@attr":{"rank":"19"},"playcount":"8"},{"mbid":"","url":"https://www.last.fm/music/Nothing","name":"Nothing","@attr":{"rank":"20"},"playcount":"8"},{"mbid":"95faba7c-5aae-43fa-9299-9451b8119fb9","url":"https://www.last.fm/music/Sweven","name":"Sweven","@attr":{"rank":"21"},"playcount":"8"},{"mbid":"0622ee96-2862-4672-821a-d0aff69e9a04","url":"https://www.last.fm/music/%C3%9Alf%C3%BA%C3%B0","name":"Úlfúð","@attr":{"rank":"22"},"playcount":"8"},{"mbid":"4dfdefcd-6a99-40c5-8b76-df5155f083d5","url":"https://www.last.fm/music/Ulthar","name":"Ulthar","@attr":{"rank":"23"},"playcount":"8"},{"mbid":"cfc5b711-a2a3-4731-ad5a-fb085f1d28ed","url":"https://www.last.fm/music/castleumbra","name":"castleumbra","@attr":{"rank":"24"},"playcount":"7"},{"mbid":"5bba23fa-23ad-4129-8a67-245d373be0ee","url":"https://www.last.fm/music/Fiddlehead","name":"Fiddlehead","@attr":{"rank":"25"},"playcount":"7"},{"mbid":"03f9e6f0-7c7f-4fd6-a47f-f0b0425f314b","url":"https://www.last.fm/music/Mis%C3%BEyrming","name":"Misþyrming","@attr":{"rank":"26"},"playcount":"6"},{"mbid":"a2bebd55-942b-48fc-abb7-bb5385decb82","url":"https://www.last.fm/music/Reverence+to+Paroxysm","name":"Reverence to Paroxysm","@attr":{"rank":"27"},"playcount":"6"},{"mbid":"68ff4824-8451-481c-b4cf-57c2c64d8c00","url":"https://www.last.fm/music/Knuckle+Puck","name":"Knuckle Puck","@attr":{"rank":"28"},"playcount":"5"},{"mbid":"","url":"https://www.last.fm/music/AFI","name":"AFI","@attr":{"rank":"29"},"playcount":"4"},{"mbid":"e37ad123-8e0d-46c6-8928-50142f4cedd7","url":"https://www.last.fm/music/Zhrine","name":"Zhrine","@attr":{"rank":"30"},"playcount":"4"},{"mbid":"b71571b2-cd6f-46ac-9adf-870bf0166d2f","url":"https://www.last.fm/music/Mortuous","name":"Mortuous","@attr":{"rank":"31"},"playcount":"3"},{"mbid":"0743b15a-3c32-48c8-ad58-cb325350befa","url":"https://www.last.fm/music/blink-182","name":"blink-182","@attr":{"rank":"32"},"playcount":"2"},{"mbid":"1cae523b-fbf3-4312-a5c9-e569a6d4bd74","url":"https://www.last.fm/music/Box+Car+Racer","name":"Box Car Racer","@attr":{"rank":"33"},"playcount":"2"},{"mbid":"194272cc-dcc8-4640-a4a6-66da7d250d5c","url":"https://www.last.fm/music/Osees","name":"Osees","@attr":{"rank":"34"},"playcount":"2"},{"mbid":"524a03b1-ceb7-4678-8aba-af87914f0c9e","url":"https://www.last.fm/music/Webbed+Wing","name":"Webbed Wing","@attr":{"rank":"35"},"playcount":"2"},{"mbid":"","url":"https://www.last.fm/music/Cancer","name":"Cancer","@attr":{"rank":"36"},"playcount":"1"},{"mbid":"7196f17e-a84b-4805-b623-7fc899f96334","url":"https://www.last.fm/music/Slow+Crush","name":"Slow Crush","@attr":{"rank":"37"},"playcount":"1"}],"@attr":{"from":"1700136000","user":"coryd_","to":"1700740800"}}},{"weeklyartistchart":{"artist":[{"mbid":"664c3e0e-42d8-48c1-b209-1efca19c0325","url":"https://www.last.fm/music/The+National","name":"The National","@attr":{"rank":"1"},"playcount":"55"},{"mbid":"f4805b9d-68f8-438e-8f13-ec7bcb4c8581","url":"https://www.last.fm/music/Damien+Jurado","name":"Damien Jurado","@attr":{"rank":"2"},"playcount":"35"},{"mbid":"194272cc-dcc8-4640-a4a6-66da7d250d5c","url":"https://www.last.fm/music/Osees","name":"Osees","@attr":{"rank":"3"},"playcount":"32"},{"mbid":"4f00bd65-db98-4f18-85ab-a3a6b8ad32a0","url":"https://www.last.fm/music/Panopticon","name":"Panopticon","@attr":{"rank":"4"},"playcount":"31"},{"mbid":"91cd46b7-30ef-4b99-a332-89512c02df2e","url":"https://www.last.fm/music/Fawn+Limbs","name":"Fawn Limbs","@attr":{"rank":"5"},"playcount":"30"},{"mbid":"","url":"https://www.last.fm/music/Cruciamentum","name":"Cruciamentum","@attr":{"rank":"6"},"playcount":"26"},{"mbid":"ec88cdc3-0517-4951-b5ef-7323e7316db0","url":"https://www.last.fm/music/Jawbreaker","name":"Jawbreaker","@attr":{"rank":"7"},"playcount":"24"},{"mbid":"3d46727d-9367-47b8-8b8b-f7b6767f7d57","url":"https://www.last.fm/music/Agalloch","name":"Agalloch","@attr":{"rank":"8"},"playcount":"23"},{"mbid":"77c167d2-4965-4421-830a-9815e4956475","url":"https://www.last.fm/music/Dinosaur+Jr.","name":"Dinosaur Jr.","@attr":{"rank":"9"},"playcount":"21"},{"mbid":"71fdb598-1967-435b-ab25-f4daad5e576b","url":"https://www.last.fm/music/Birds+in+Row","name":"Birds in Row","@attr":{"rank":"10"},"playcount":"13"},{"mbid":"c80f38a6-9980-485d-997c-5c1a9cbd0d64","url":"https://www.last.fm/music/Ryan+Adams","name":"Ryan Adams","@attr":{"rank":"11"},"playcount":"13"},{"mbid":"af8fd97c-db72-4e30-b2aa-30ebd0c4f1a0","url":"https://www.last.fm/music/Darkthrone","name":"Darkthrone","@attr":{"rank":"12"},"playcount":"11"},{"mbid":"7f2a8098-50e3-451c-8696-c5d9f64f4762","url":"https://www.last.fm/music/Wire","name":"Wire","@attr":{"rank":"13"},"playcount":"11"},{"mbid":"","url":"https://www.last.fm/music/Funebre","name":"Funebre","@attr":{"rank":"14"},"playcount":"10"},{"mbid":"64d475ac-2678-4535-b220-009a098a5b44","url":"https://www.last.fm/music/Worm","name":"Worm","@attr":{"rank":"15"},"playcount":"9"},{"mbid":"c91d4c04-23c6-4b8c-b154-613be951f8fd","url":"https://www.last.fm/music/Universally+Estranged","name":"Universally Estranged","@attr":{"rank":"16"},"playcount":"8"},{"mbid":"","url":"https://www.last.fm/music/Soul+Blind","name":"Soul Blind","@attr":{"rank":"17"},"playcount":"7"},{"mbid":"20244d07-534f-4eff-b4d4-930878889970","url":"https://www.last.fm/music/Taylor+Swift","name":"Taylor Swift","@attr":{"rank":"18"},"playcount":"6"},{"mbid":"0743b15a-3c32-48c8-ad58-cb325350befa","url":"https://www.last.fm/music/blink-182","name":"blink-182","@attr":{"rank":"19"},"playcount":"1"},{"mbid":"f0b1c181-9d14-4504-bf00-abac3e64dc24","url":"https://www.last.fm/music/Cryptic+Shift","name":"Cryptic Shift","@attr":{"rank":"20"},"playcount":"1"},{"mbid":"d475788f-837d-4f96-9eec-2f5e32d7d163","url":"https://www.last.fm/music/Imperial+Triumphant","name":"Imperial Triumphant","@attr":{"rank":"21"},"playcount":"1"},{"mbid":"96855c21-b832-4366-ba12-0d2330c36a86","url":"https://www.last.fm/music/Phoebe+Bridgers","name":"Phoebe Bridgers","@attr":{"rank":"22"},"playcount":"1"}],"@attr":{"from":"1700740800","user":"coryd_","to":"1701345600"}}},{"weeklyartistchart":{"artist":[{"mbid":"0743b15a-3c32-48c8-ad58-cb325350befa","url":"https://www.last.fm/music/blink-182","name":"blink-182","@attr":{"rank":"1"},"playcount":"42"},{"mbid":"4d2949b4-eb5f-4296-b71a-04603c6a9802","url":"https://www.last.fm/music/Rotten+Sound","name":"Rotten Sound","@attr":{"rank":"2"},"playcount":"40"},{"mbid":"0f3f7357-73d3-42a3-81a5-b359bc4e8a56","url":"https://www.last.fm/music/Portrayal+of+Guilt","name":"Portrayal of Guilt","@attr":{"rank":"3"},"playcount":"39"},{"mbid":"","url":"https://www.last.fm/music/Envy","name":"Envy","@attr":{"rank":"4"},"playcount":"35"},{"mbid":"143fd9a0-28a4-42fb-911e-e5c00baf06f9","url":"https://www.last.fm/music/Wormrot","name":"Wormrot","@attr":{"rank":"5"},"playcount":"32"},{"mbid":"175d039d-2f0e-4423-a31c-b1a87fc28bb0","url":"https://www.last.fm/music/Helfr%C3%B3","name":"Helfró","@attr":{"rank":"6"},"playcount":"25"},{"mbid":"b436354f-bf4a-44c0-a77d-7f7b3c38b498","url":"https://www.last.fm/music/Gravenchalice","name":"Gravenchalice","@attr":{"rank":"7"},"playcount":"23"},{"mbid":"5f601c8d-24af-4eb6-a2bb-f7e04ad40ed8","url":"https://www.last.fm/music/Afsky","name":"Afsky","@attr":{"rank":"8"},"playcount":"20"},{"mbid":"fa31e7d4-a03a-4110-98fc-f8826e95ec25","url":"https://www.last.fm/music/Converge","name":"Converge","@attr":{"rank":"9"},"playcount":"19"},{"mbid":"ce38e067-8e83-4660-8852-0c1db7ddaadb","url":"https://www.last.fm/music/Edge+of+Sanity","name":"Edge of Sanity","@attr":{"rank":"10"},"playcount":"19"},{"mbid":"","url":"https://www.last.fm/music/Full+of+Hell+&+Nothing","name":"Full of Hell & Nothing","@attr":{"rank":"11"},"playcount":"18"},{"mbid":"c91d4c04-23c6-4b8c-b154-613be951f8fd","url":"https://www.last.fm/music/Universally+Estranged","name":"Universally Estranged","@attr":{"rank":"12"},"playcount":"17"},{"mbid":"37c78aeb-d196-42b5-b991-6afb4fc9bc2e","url":"https://www.last.fm/music/Dead+Kennedys","name":"Dead Kennedys","@attr":{"rank":"13"},"playcount":"16"},{"mbid":"57805d77-f947-4851-b7fb-78baad154451","url":"https://www.last.fm/music/The+Ataris","name":"The Ataris","@attr":{"rank":"14"},"playcount":"15"},{"mbid":"5c0d3974-33d5-4f7a-bebc-8f50c057927e","url":"https://www.last.fm/music/Pig+Destroyer","name":"Pig Destroyer","@attr":{"rank":"15"},"playcount":"14"},{"mbid":"dc0d05ce-2f47-4962-b4fa-8631a0a51987","url":"https://www.last.fm/music/The+Replacements","name":"The Replacements","@attr":{"rank":"16"},"playcount":"14"},{"mbid":"926985c7-9385-481f-b6e9-dfed167bd9c0","url":"https://www.last.fm/music/Phobophilic","name":"Phobophilic","@attr":{"rank":"17"},"playcount":"13"},{"mbid":"a449014f-de9a-43fa-b271-786b0af10926","url":"https://www.last.fm/music/Undeath","name":"Undeath","@attr":{"rank":"18"},"playcount":"13"},{"mbid":"ba0d6274-db14-4ef5-b28d-657ebde1a396","url":"https://www.last.fm/music/The+Smashing+Pumpkins","name":"The Smashing Pumpkins","@attr":{"rank":"19"},"playcount":"12"},{"mbid":"64efc1cc-30e3-46c7-b783-178e41f0af6a","url":"https://www.last.fm/music/Outer+Heaven","name":"Outer Heaven","@attr":{"rank":"20"},"playcount":"11"},{"mbid":"08ac1e0c-f21d-48cd-aacb-1c858017dea6","url":"https://www.last.fm/music/Molested","name":"Molested","@attr":{"rank":"21"},"playcount":"9"},{"mbid":"b4e4b359-76a3-447e-be1d-80a24887134e","url":"https://www.last.fm/music/Krallice","name":"Krallice","@attr":{"rank":"22"},"playcount":"8"},{"mbid":"5cefb002-9b9f-4313-9348-4c99d57071d9","url":"https://www.last.fm/music/Drastus","name":"Drastus","@attr":{"rank":"23"},"playcount":"7"},{"mbid":"18ccf49d-dc54-4ee4-9b43-2c8194af97fb","url":"https://www.last.fm/music/Heaven+in+Her+Arms","name":"Heaven in Her Arms","@attr":{"rank":"24"},"playcount":"7"},{"mbid":"f66d378e-d9f0-4c5d-a4b9-0ee1b9fb2e09","url":"https://www.last.fm/music/Anxious","name":"Anxious","@attr":{"rank":"25"},"playcount":"6"},{"mbid":"2453b989-c41a-4aa1-8ef7-0bc4437e1d02","url":"https://www.last.fm/music/Carpe+Noctem","name":"Carpe Noctem","@attr":{"rank":"26"},"playcount":"6"},{"mbid":"3dc68299-2dda-424b-bfb9-b8ac21c15d21","url":"https://www.last.fm/music/Noltem","name":"Noltem","@attr":{"rank":"27"},"playcount":"6"},{"mbid":"6fcedda5-9c36-4c4b-bde3-e8e767b86519","url":"https://www.last.fm/music/Andavald","name":"Andavald","@attr":{"rank":"28"},"playcount":"5"},{"mbid":"d2c944b5-7475-47bd-b3bf-df1b68f80a68","url":"https://www.last.fm/music/Narrow+Head","name":"Narrow Head","@attr":{"rank":"29"},"playcount":"5"},{"mbid":"","url":"https://www.last.fm/music/Oasis","name":"Oasis","@attr":{"rank":"30"},"playcount":"5"},{"mbid":"5c9dd772-a38f-4873-baa8-4b5d9dff3990","url":"https://www.last.fm/music/Spanish+Love+Songs","name":"Spanish Love Songs","@attr":{"rank":"31"},"playcount":"4"},{"mbid":"","url":"https://www.last.fm/music/Adramelech","name":"Adramelech","@attr":{"rank":"32"},"playcount":"3"},{"mbid":"70248960-cb53-4ea4-943a-edb18f7d336f","url":"https://www.last.fm/music/Bruce+Springsteen","name":"Bruce Springsteen","@attr":{"rank":"33"},"playcount":"3"},{"mbid":"7b522171-aca2-45de-8ab4-d73001f04886","url":"https://www.last.fm/music/Carnal+Tomb","name":"Carnal Tomb","@attr":{"rank":"34"},"playcount":"3"},{"mbid":"c6e886dd-7f35-4f7f-803f-5696423178d5","url":"https://www.last.fm/music/Cosmic+Putrefaction","name":"Cosmic Putrefaction","@attr":{"rank":"35"},"playcount":"3"},{"mbid":"524a03b1-ceb7-4678-8aba-af87914f0c9e","url":"https://www.last.fm/music/Webbed+Wing","name":"Webbed Wing","@attr":{"rank":"36"},"playcount":"3"},{"mbid":"","url":"https://www.last.fm/music/home+is+where","name":"home is where","@attr":{"rank":"37"},"playcount":"2"},{"mbid":"3d682644-14ed-4844-b897-a91d8401ef02","url":"https://www.last.fm/music/State+Faults","name":"State Faults","@attr":{"rank":"38"},"playcount":"2"},{"mbid":"2ec89bcc-5bf9-4d2a-ac5e-44b7496d115a","url":"https://www.last.fm/music/La+Dispute","name":"La Dispute","@attr":{"rank":"39"},"playcount":"1"}],"@attr":{"from":"1701345600","user":"coryd_","to":"1701950400"}}},{"weeklyartistchart":{"artist":[{"mbid":"9e86aeef-99ec-419e-9ce3-25d21bc5665f","url":"https://www.last.fm/music/Inculter","name":"Inculter","@attr":{"rank":"1"},"playcount":"42"},{"mbid":"864aa861-e22a-4187-8baa-2ef0c215bc0a","url":"https://www.last.fm/music/Godflesh","name":"Godflesh","@attr":{"rank":"2"},"playcount":"33"},{"mbid":"fa31e7d4-a03a-4110-98fc-f8826e95ec25","url":"https://www.last.fm/music/Converge","name":"Converge","@attr":{"rank":"3"},"playcount":"31"},{"mbid":"c373c7f0-fddf-4c04-a327-19dd83590753","url":"https://www.last.fm/music/Immolation","name":"Immolation","@attr":{"rank":"4"},"playcount":"29"},{"mbid":"1ca441fa-7cea-4f29-939b-06d8741f74c7","url":"https://www.last.fm/music/Free+Throw","name":"Free Throw","@attr":{"rank":"5"},"playcount":"23"},{"mbid":"","url":"https://www.last.fm/music/AFI","name":"AFI","@attr":{"rank":"6"},"playcount":"21"},{"mbid":"","url":"https://www.last.fm/music/home+is+where","name":"home is where","@attr":{"rank":"7"},"playcount":"13"},{"mbid":"c16dcdae-a651-42c1-aff8-edda0f463157","url":"https://www.last.fm/music/Soft+Kill","name":"Soft Kill","@attr":{"rank":"8"},"playcount":"12"},{"mbid":"d347406f-839d-4423-9a28-188939282afa","url":"https://www.last.fm/music/Cult+of+Luna","name":"Cult of Luna","@attr":{"rank":"9"},"playcount":"10"},{"mbid":"","url":"https://www.last.fm/music/Nothing","name":"Nothing","@attr":{"rank":"10"},"playcount":"10"},{"mbid":"c07f0676-9143-4217-8a9f-4c26bd636f13","url":"https://www.last.fm/music/My+Chemical+Romance","name":"My Chemical Romance","@attr":{"rank":"11"},"playcount":"9"},{"mbid":"","url":"https://www.last.fm/music/Altars","name":"Altars","@attr":{"rank":"12"},"playcount":"8"},{"mbid":"600f4614-1353-486c-9402-e2c684e89f04","url":"https://www.last.fm/music/Phrenelith","name":"Phrenelith","@attr":{"rank":"13"},"playcount":"8"},{"mbid":"ec271222-b956-44d8-a30f-ad863c42c647","url":"https://www.last.fm/music/Lamp+Of+Murmuur","name":"Lamp Of Murmuur","@attr":{"rank":"14"},"playcount":"6"},{"mbid":"aba64937-3334-4c65-90a1-4e6b9d4d7ada","url":"https://www.last.fm/music/Aesop+Rock","name":"Aesop Rock","@attr":{"rank":"15"},"playcount":"5"},{"mbid":"0ff3ab56-3185-4db1-a879-808242e878d0","url":"https://www.last.fm/music/Carbonized","name":"Carbonized","@attr":{"rank":"16"},"playcount":"5"},{"mbid":"f4ccf6c5-ad41-4f8f-bb9e-6e2c6ad23302","url":"https://www.last.fm/music/Deafheaven","name":"Deafheaven","@attr":{"rank":"17"},"playcount":"4"},{"mbid":"664c3e0e-42d8-48c1-b209-1efca19c0325","url":"https://www.last.fm/music/The+National","name":"The National","@attr":{"rank":"18"},"playcount":"4"},{"mbid":"f4805b9d-68f8-438e-8f13-ec7bcb4c8581","url":"https://www.last.fm/music/Damien+Jurado","name":"Damien Jurado","@attr":{"rank":"19"},"playcount":"3"},{"mbid":"8829b107-5bbf-4a4b-9e39-0ad07d447fb8","url":"https://www.last.fm/music/VoidCeremony","name":"VoidCeremony","@attr":{"rank":"20"},"playcount":"3"},{"mbid":"3d46727d-9367-47b8-8b8b-f7b6767f7d57","url":"https://www.last.fm/music/Agalloch","name":"Agalloch","@attr":{"rank":"21"},"playcount":"2"},{"mbid":"68ff4824-8451-481c-b4cf-57c2c64d8c00","url":"https://www.last.fm/music/Knuckle+Puck","name":"Knuckle Puck","@attr":{"rank":"22"},"playcount":"2"},{"mbid":"a8c4f4c9-b18a-4edf-a7d1-f5b657a9503b","url":"https://www.last.fm/music/oso+oso","name":"oso oso","@attr":{"rank":"23"},"playcount":"2"},{"mbid":"e11c6f03-0bcd-44ca-b4fb-9446fdf08af5","url":"https://www.last.fm/music/Ved+Buens+Ende","name":"Ved Buens Ende","@attr":{"rank":"24"},"playcount":"2"},{"mbid":"adc94368-3568-4d92-9f2a-f50a27b8be68","url":"https://www.last.fm/music/Dephosphorus","name":"Dephosphorus","@attr":{"rank":"25"},"playcount":"1"},{"mbid":"169c4c28-858e-497b-81a4-8bc15e0026ea","url":"https://www.last.fm/music/Porcupine+Tree","name":"Porcupine Tree","@attr":{"rank":"26"},"playcount":"1"},{"mbid":"","url":"https://www.last.fm/music/Rush","name":"Rush","@attr":{"rank":"27"},"playcount":"1"}],"@attr":{"from":"1701950400","user":"coryd_","to":"1702555200"}}},{"weeklyartistchart":{"artist":[{"mbid":"c5119d8a-ffee-48bc-99c3-f323bdf16d82","url":"https://www.last.fm/music/Vektor","name":"Vektor","@attr":{"rank":"1"},"playcount":"61"},{"mbid":"","url":"https://www.last.fm/music/AFI","name":"AFI","@attr":{"rank":"2"},"playcount":"32"},{"mbid":"bc5e2ad6-0a4a-4d90-b911-e9a7e6861727","url":"https://www.last.fm/music/Mastodon","name":"Mastodon","@attr":{"rank":"3"},"playcount":"27"},{"mbid":"f8ad39f6-1ac4-418e-a603-c80dd09b94a9","url":"https://www.last.fm/music/Gudsforladt","name":"Gudsforladt","@attr":{"rank":"4"},"playcount":"26"},{"mbid":"","url":"https://www.last.fm/music/Nucleus","name":"Nucleus","@attr":{"rank":"5"},"playcount":"25"},{"mbid":"4f00bd65-db98-4f18-85ab-a3a6b8ad32a0","url":"https://www.last.fm/music/Panopticon","name":"Panopticon","@attr":{"rank":"6"},"playcount":"22"},{"mbid":"77c167d2-4965-4421-830a-9815e4956475","url":"https://www.last.fm/music/Dinosaur+Jr.","name":"Dinosaur Jr.","@attr":{"rank":"7"},"playcount":"20"},{"mbid":"","url":"https://www.last.fm/music/Obliteration","name":"Obliteration","@attr":{"rank":"8"},"playcount":"16"},{"mbid":"a80c5dc5-b12e-4667-9f5a-b568961f3839","url":"https://www.last.fm/music/Run+the+Jewels","name":"Run the Jewels","@attr":{"rank":"9"},"playcount":"16"},{"mbid":"0743b15a-3c32-48c8-ad58-cb325350befa","url":"https://www.last.fm/music/blink-182","name":"blink-182","@attr":{"rank":"10"},"playcount":"15"},{"mbid":"78783494-b757-4d0b-9a74-12261a851e4c","url":"https://www.last.fm/music/Suffering+Hour","name":"Suffering Hour","@attr":{"rank":"11"},"playcount":"15"},{"mbid":"d50a4b89-ff1f-4659-9fde-f76f8d5b3c89","url":"https://www.last.fm/music/Carcass","name":"Carcass","@attr":{"rank":"12"},"playcount":"14"},{"mbid":"4de7df66-b805-4183-87af-ac38477b624a","url":"https://www.last.fm/music/Frail+Body","name":"Frail Body","@attr":{"rank":"13"},"playcount":"14"},{"mbid":"69228a53-5c21-421d-ad9d-c085c6bde556","url":"https://www.last.fm/music/Gutter+Instinct","name":"Gutter Instinct","@attr":{"rank":"14"},"playcount":"14"},{"mbid":"218dfcea-97f4-4426-9cab-a50c11d92555","url":"https://www.last.fm/music/Temisto","name":"Temisto","@attr":{"rank":"15"},"playcount":"14"},{"mbid":"9e86aeef-99ec-419e-9ce3-25d21bc5665f","url":"https://www.last.fm/music/Inculter","name":"Inculter","@attr":{"rank":"16"},"playcount":"9"},{"mbid":"3e6d10aa-1c33-48cb-b9d9-0182ec44cda7","url":"https://www.last.fm/music/Corpsessed","name":"Corpsessed","@attr":{"rank":"17"},"playcount":"4"},{"mbid":"66cb12f6-6502-486d-bf67-efd5bdaee6ac","url":"https://www.last.fm/music/Voivod","name":"Voivod","@attr":{"rank":"18"},"playcount":"3"},{"mbid":"c2a44e93-3a2b-44aa-bd8b-7a71bb76e3b5","url":"https://www.last.fm/music/%252B44","name":"+44","@attr":{"rank":"19"},"playcount":"2"},{"mbid":"c3f28da8-662d-4f09-bdc7-3084bf685930","url":"https://www.last.fm/music/Iron+&+Wine","name":"Iron & Wine","@attr":{"rank":"20"},"playcount":"2"},{"mbid":"bad96c62-50f8-4159-b155-3ffb63c698f8","url":"https://www.last.fm/music/J+Church","name":"J Church","@attr":{"rank":"21"},"playcount":"2"},{"mbid":"561d854a-6a28-4aa7-8c99-323e6ce46c2a","url":"https://www.last.fm/music/Miles+Davis","name":"Miles Davis","@attr":{"rank":"22"},"playcount":"2"},{"mbid":"","url":"https://www.last.fm/music/Oasis","name":"Oasis","@attr":{"rank":"23"},"playcount":"2"},{"mbid":"","url":"https://www.last.fm/music/Autopsy","name":"Autopsy","@attr":{"rank":"24"},"playcount":"1"},{"mbid":"","url":"https://www.last.fm/music/Behemoth","name":"Behemoth","@attr":{"rank":"25"},"playcount":"1"},{"mbid":"b1003bf1-25b8-41f4-a783-36060f987913","url":"https://www.last.fm/music/City+and+Colour","name":"City and Colour","@attr":{"rank":"26"},"playcount":"1"},{"mbid":"c12476fc-3f8d-4340-8dba-883bdee08ee7","url":"https://www.last.fm/music/Demilich","name":"Demilich","@attr":{"rank":"27"},"playcount":"1"},{"mbid":"66527b12-8dc9-4e0d-8d19-a7eb9a89ba28","url":"https://www.last.fm/music/Extremity","name":"Extremity","@attr":{"rank":"28"},"playcount":"1"},{"mbid":"37e9d7b2-7779-41b2-b2eb-3685351caad3","url":"https://www.last.fm/music/NoMeansNo","name":"NoMeansNo","@attr":{"rank":"29"},"playcount":"1"},{"mbid":"96855c21-b832-4366-ba12-0d2330c36a86","url":"https://www.last.fm/music/Phoebe+Bridgers","name":"Phoebe Bridgers","@attr":{"rank":"30"},"playcount":"1"},{"mbid":"8ed03ec1-b8c7-4fe3-a0ac-23415ebbb9f7","url":"https://www.last.fm/music/Pity+Sex","name":"Pity Sex","@attr":{"rank":"31"},"playcount":"1"},{"mbid":"af63ec4d-9fe4-4001-bcb6-8dd160ee6451","url":"https://www.last.fm/music/The+Hotelier","name":"The Hotelier","@attr":{"rank":"32"},"playcount":"1"},{"mbid":"d10a7b78-aee5-4a37-b9ee-a962ef2ca5d7","url":"https://www.last.fm/music/Tideless","name":"Tideless","@attr":{"rank":"33"},"playcount":"1"}],"@attr":{"from":"1702555200","user":"coryd_","to":"1703160000"}}},{"weeklyartistchart":{"artist":[{"mbid":"0743b15a-3c32-48c8-ad58-cb325350befa","url":"https://www.last.fm/music/blink-182","name":"blink-182","@attr":{"rank":"1"},"playcount":"21"},{"mbid":"7b522171-aca2-45de-8ab4-d73001f04886","url":"https://www.last.fm/music/Carnal+Tomb","name":"Carnal Tomb","@attr":{"rank":"2"},"playcount":"21"},{"mbid":"68ff4824-8451-481c-b4cf-57c2c64d8c00","url":"https://www.last.fm/music/Knuckle+Puck","name":"Knuckle Puck","@attr":{"rank":"3"},"playcount":"19"},{"mbid":"6eb62b38-707f-42c0-b9c9-417df8a2a0c6","url":"https://www.last.fm/music/Cerebral+Rot","name":"Cerebral Rot","@attr":{"rank":"4"},"playcount":"18"},{"mbid":"","url":"https://www.last.fm/music/Rush","name":"Rush","@attr":{"rank":"5"},"playcount":"18"},{"mbid":"","url":"https://www.last.fm/music/Basement","name":"Basement","@attr":{"rank":"6"},"playcount":"16"},{"mbid":"32d2897c-4c91-46db-8161-f51d3f4f0d93","url":"https://www.last.fm/music/Drug+Church","name":"Drug Church","@attr":{"rank":"7"},"playcount":"16"},{"mbid":"c16dcdae-a651-42c1-aff8-edda0f463157","url":"https://www.last.fm/music/Soft+Kill","name":"Soft Kill","@attr":{"rank":"8"},"playcount":"15"},{"mbid":"5c9dd772-a38f-4873-baa8-4b5d9dff3990","url":"https://www.last.fm/music/Spanish+Love+Songs","name":"Spanish Love Songs","@attr":{"rank":"9"},"playcount":"13"},{"mbid":"71fdb598-1967-435b-ab25-f4daad5e576b","url":"https://www.last.fm/music/Birds+in+Row","name":"Birds in Row","@attr":{"rank":"10"},"playcount":"11"},{"mbid":"5441c29d-3602-4898-b1a1-b77fa23b8e50","url":"https://www.last.fm/music/David+Bowie","name":"David Bowie","@attr":{"rank":"11"},"playcount":"10"},{"mbid":"96855c21-b832-4366-ba12-0d2330c36a86","url":"https://www.last.fm/music/Phoebe+Bridgers","name":"Phoebe Bridgers","@attr":{"rank":"12"},"playcount":"9"},{"mbid":"69ee3720-a7cb-4402-b48d-a02c366f2bcf","url":"https://www.last.fm/music/The+Cure","name":"The Cure","@attr":{"rank":"13"},"playcount":"8"},{"mbid":"bc5e2ad6-0a4a-4d90-b911-e9a7e6861727","url":"https://www.last.fm/music/Mastodon","name":"Mastodon","@attr":{"rank":"14"},"playcount":"7"},{"mbid":"a0327dc2-dc76-44d5-aec6-47cd2dff1469","url":"https://www.last.fm/music/Counting+Crows","name":"Counting Crows","@attr":{"rank":"15"},"playcount":"6"},{"mbid":"2ec89bcc-5bf9-4d2a-ac5e-44b7496d115a","url":"https://www.last.fm/music/La+Dispute","name":"La Dispute","@attr":{"rank":"16"},"playcount":"4"},{"mbid":"72c536dc-7137-4477-a521-567eeb840fa8","url":"https://www.last.fm/music/Bob+Dylan","name":"Bob Dylan","@attr":{"rank":"17"},"playcount":"3"},{"mbid":"","url":"https://www.last.fm/music/AFI","name":"AFI","@attr":{"rank":"18"},"playcount":"1"},{"mbid":"","url":"https://www.last.fm/music/Cruciamentum","name":"Cruciamentum","@attr":{"rank":"19"},"playcount":"1"},{"mbid":"","url":"https://www.last.fm/music/Soul+Blind","name":"Soul Blind","@attr":{"rank":"20"},"playcount":"1"}],"@attr":{"from":"1703160000","user":"coryd_","to":"1703764800"}}},{"weeklyartistchart":{"artist":[{"mbid":"4d2949b4-eb5f-4296-b71a-04603c6a9802","url":"https://www.last.fm/music/Rotten+Sound","name":"Rotten Sound","@attr":{"rank":"1"},"playcount":"45"},{"mbid":"66cb12f6-6502-486d-bf67-efd5bdaee6ac","url":"https://www.last.fm/music/Voivod","name":"Voivod","@attr":{"rank":"2"},"playcount":"34"},{"mbid":"e652c211-44cf-4a4e-9ef5-57ea4a9fb2db","url":"https://www.last.fm/music/Glassing","name":"Glassing","@attr":{"rank":"3"},"playcount":"31"},{"mbid":"37e9d7b2-7779-41b2-b2eb-3685351caad3","url":"https://www.last.fm/music/NoMeansNo","name":"NoMeansNo","@attr":{"rank":"4"},"playcount":"28"},{"mbid":"546e82a3-550b-4cf2-8cb8-595d9d32aa49","url":"https://www.last.fm/music/Fleshwater","name":"Fleshwater","@attr":{"rank":"5"},"playcount":"26"},{"mbid":"cc546218-cc08-4ae9-9592-ac1596c1470d","url":"https://www.last.fm/music/Propagandhi","name":"Propagandhi","@attr":{"rank":"6"},"playcount":"25"},{"mbid":"7bfc9a9a-ee6a-4a0a-8643-9d790c8d956f","url":"https://www.last.fm/music/Hyperdontia","name":"Hyperdontia","@attr":{"rank":"7"},"playcount":"23"},{"mbid":"30b6f843-7116-4c8d-b157-f32a6e4fee4a","url":"https://www.last.fm/music/Cryptworm","name":"Cryptworm","@attr":{"rank":"8"},"playcount":"22"},{"mbid":"7961aa2c-36d4-4601-a691-981b18143991","url":"https://www.last.fm/music/Galvanizer","name":"Galvanizer","@attr":{"rank":"9"},"playcount":"21"},{"mbid":"f6e61750-a6b7-4d88-979b-052345cd0e4a","url":"https://www.last.fm/music/Sturgill+Simpson","name":"Sturgill Simpson","@attr":{"rank":"10"},"playcount":"21"},{"mbid":"","url":"https://www.last.fm/music/Rush","name":"Rush","@attr":{"rank":"11"},"playcount":"20"},{"mbid":"f5a19292-1b45-466b-8732-a80d0eb4eec2","url":"https://www.last.fm/music/Funebrarum","name":"Funebrarum","@attr":{"rank":"12"},"playcount":"19"},{"mbid":"aeab43f2-ef38-4a4d-b2cb-814d126df1c1","url":"https://www.last.fm/music/Golgothan+Remains","name":"Golgothan Remains","@attr":{"rank":"13"},"playcount":"19"},{"mbid":"","url":"https://www.last.fm/music/AFI","name":"AFI","@attr":{"rank":"14"},"playcount":"18"},{"mbid":"2aaf7396-6ab8-40f3-9776-a41c42c8e26b","url":"https://www.last.fm/music/LCD+Soundsystem","name":"LCD Soundsystem","@attr":{"rank":"15"},"playcount":"17"},{"mbid":"680fbad9-61d5-4e6f-ac83-ed903aeb049b","url":"https://www.last.fm/music/Undergang","name":"Undergang","@attr":{"rank":"16"},"playcount":"15"},{"mbid":"","url":"https://www.last.fm/music/Envy","name":"Envy","@attr":{"rank":"17"},"playcount":"9"},{"mbid":"26eaa84f-25e4-4311-b5d6-d184d146c7c0","url":"https://www.last.fm/music/Gorephilia","name":"Gorephilia","@attr":{"rank":"18"},"playcount":"9"},{"mbid":"91cd46b7-30ef-4b99-a332-89512c02df2e","url":"https://www.last.fm/music/Fawn+Limbs","name":"Fawn Limbs","@attr":{"rank":"19"},"playcount":"6"},{"mbid":"9e86aeef-99ec-419e-9ce3-25d21bc5665f","url":"https://www.last.fm/music/Inculter","name":"Inculter","@attr":{"rank":"20"},"playcount":"5"},{"mbid":"67349203-0c02-48d9-a0ac-4ff40bac0905","url":"https://www.last.fm/music/Disillusion","name":"Disillusion","@attr":{"rank":"21"},"playcount":"4"},{"mbid":"","url":"https://www.last.fm/music/Behemoth","name":"Behemoth","@attr":{"rank":"22"},"playcount":"3"},{"mbid":"29bb04d6-5602-464c-8577-f55a27511b27","url":"https://www.last.fm/music/Enslaved","name":"Enslaved","@attr":{"rank":"23"},"playcount":"3"},{"mbid":"c5119d8a-ffee-48bc-99c3-f323bdf16d82","url":"https://www.last.fm/music/Vektor","name":"Vektor","@attr":{"rank":"24"},"playcount":"3"},{"mbid":"71fdb598-1967-435b-ab25-f4daad5e576b","url":"https://www.last.fm/music/Birds+in+Row","name":"Birds in Row","@attr":{"rank":"25"},"playcount":"2"},{"mbid":"2ec89bcc-5bf9-4d2a-ac5e-44b7496d115a","url":"https://www.last.fm/music/La+Dispute","name":"La Dispute","@attr":{"rank":"26"},"playcount":"1"}],"@attr":{"from":"1703764800","user":"coryd_","to":"1704369600"}}},{"weeklyartistchart":{"artist":[{"mbid":"143fd9a0-28a4-42fb-911e-e5c00baf06f9","url":"https://www.last.fm/music/Wormrot","name":"Wormrot","@attr":{"rank":"1"},"playcount":"47"},{"mbid":"37e9d7b2-7779-41b2-b2eb-3685351caad3","url":"https://www.last.fm/music/NoMeansNo","name":"NoMeansNo","@attr":{"rank":"2"},"playcount":"42"},{"mbid":"37ea73dd-a48c-4659-8b9d-5c77bd9cbd12","url":"https://www.last.fm/music/Deathspell+Omega","name":"Deathspell Omega","@attr":{"rank":"3"},"playcount":"40"},{"mbid":"","url":"https://www.last.fm/music/Autopsy","name":"Autopsy","@attr":{"rank":"4"},"playcount":"37"},{"mbid":"0743b15a-3c32-48c8-ad58-cb325350befa","url":"https://www.last.fm/music/blink-182","name":"blink-182","@attr":{"rank":"5"},"playcount":"36"},{"mbid":"4dfdefcd-6a99-40c5-8b76-df5155f083d5","url":"https://www.last.fm/music/Ulthar","name":"Ulthar","@attr":{"rank":"6"},"playcount":"24"},{"mbid":"","url":"https://www.last.fm/music/Inanna","name":"Inanna","@attr":{"rank":"7"},"playcount":"22"},{"mbid":"68ff4824-8451-481c-b4cf-57c2c64d8c00","url":"https://www.last.fm/music/Knuckle+Puck","name":"Knuckle Puck","@attr":{"rank":"8"},"playcount":"17"},{"mbid":"75042f03-597a-4e1c-bc5d-4a62f4df05b6","url":"https://www.last.fm/music/Oathbreaker","name":"Oathbreaker","@attr":{"rank":"9"},"playcount":"15"},{"mbid":"211757b0-8899-44a0-befc-923a558170c0","url":"https://www.last.fm/music/Venenum","name":"Venenum","@attr":{"rank":"10"},"playcount":"14"},{"mbid":"e9d2cdf6-d485-4074-9a53-9990c9a4d8b1","url":"https://www.last.fm/music/Oranssi+Pazuzu","name":"Oranssi Pazuzu","@attr":{"rank":"11"},"playcount":"13"},{"mbid":"680fbad9-61d5-4e6f-ac83-ed903aeb049b","url":"https://www.last.fm/music/Undergang","name":"Undergang","@attr":{"rank":"12"},"playcount":"13"},{"mbid":"","url":"https://www.last.fm/music/Rush","name":"Rush","@attr":{"rank":"13"},"playcount":"12"},{"mbid":"eb263937-f7e8-416f-b9f7-67334cf0d076","url":"https://www.last.fm/music/Afflicted","name":"Afflicted","@attr":{"rank":"14"},"playcount":"11"},{"mbid":"","url":"https://www.last.fm/music/Cruciamentum","name":"Cruciamentum","@attr":{"rank":"15"},"playcount":"10"},{"mbid":"424373ba-10fc-4883-bb33-af5a1977719b","url":"https://www.last.fm/music/Infester","name":"Infester","@attr":{"rank":"16"},"playcount":"10"},{"mbid":"","url":"https://www.last.fm/music/Obliteration","name":"Obliteration","@attr":{"rank":"17"},"playcount":"10"},{"mbid":"565ac6c2-e47d-4b5f-99f1-24afdf97903a","url":"https://www.last.fm/music/Sedimentum","name":"Sedimentum","@attr":{"rank":"18"},"playcount":"9"},{"mbid":"4387b544-e4d0-4f18-b74e-d4a5ba1582ab","url":"https://www.last.fm/music/Traveling+Wilburys","name":"Traveling Wilburys","@attr":{"rank":"19"},"playcount":"9"},{"mbid":"2280ca0e-6968-4349-8c36-cb0cbd6ee95f","url":"https://www.last.fm/music/Jello+Biafra+With+Nomeansno","name":"Jello Biafra With Nomeansno","@attr":{"rank":"20"},"playcount":"8"},{"mbid":"68d258b4-d6cd-4a05-9cc0-98c2e1f1993a","url":"https://www.last.fm/music/Chaotian","name":"Chaotian","@attr":{"rank":"21"},"playcount":"7"},{"mbid":"2756518c-7d46-42e2-8357-184fc9aeade0","url":"https://www.last.fm/music/Jordablod","name":"Jordablod","@attr":{"rank":"22"},"playcount":"7"},{"mbid":"c837c0fa-74dd-483b-95f7-25a46f92fa88","url":"https://www.last.fm/music/Prince+Daddy+&+The+Hyena","name":"Prince Daddy & The Hyena","@attr":{"rank":"23"},"playcount":"7"},{"mbid":"8331d770-f379-420c-aabc-d8c1ebdc12f3","url":"https://www.last.fm/music/Vacuous","name":"Vacuous","@attr":{"rank":"24"},"playcount":"7"},{"mbid":"29616e0c-78d6-4c5f-99e2-d9e113d19d6a","url":"https://www.last.fm/music/Vircolac","name":"Vircolac","@attr":{"rank":"25"},"playcount":"7"},{"mbid":"561d854a-6a28-4aa7-8c99-323e6ce46c2a","url":"https://www.last.fm/music/Miles+Davis","name":"Miles Davis","@attr":{"rank":"26"},"playcount":"2"},{"mbid":"d347406f-839d-4423-9a28-188939282afa","url":"https://www.last.fm/music/Cult+of+Luna","name":"Cult of Luna","@attr":{"rank":"27"},"playcount":"1"}],"@attr":{"from":"1704369600","user":"coryd_","to":"1704974400"}}},{"weeklyartistchart":{"artist":[{"mbid":"1ca441fa-7cea-4f29-939b-06d8741f74c7","url":"https://www.last.fm/music/Free+Throw","name":"Free Throw","@attr":{"rank":"1"},"playcount":"34"},{"mbid":"c373c7f0-fddf-4c04-a327-19dd83590753","url":"https://www.last.fm/music/Immolation","name":"Immolation","@attr":{"rank":"2"},"playcount":"34"},{"mbid":"32d2897c-4c91-46db-8161-f51d3f4f0d93","url":"https://www.last.fm/music/Drug+Church","name":"Drug Church","@attr":{"rank":"3"},"playcount":"28"},{"mbid":"","url":"https://www.last.fm/music/Envy","name":"Envy","@attr":{"rank":"4"},"playcount":"26"},{"mbid":"86139012-695b-42f4-98f1-1f353f7230b4","url":"https://www.last.fm/music/Eluvium","name":"Eluvium","@attr":{"rank":"5"},"playcount":"20"},{"mbid":"0743b15a-3c32-48c8-ad58-cb325350befa","url":"https://www.last.fm/music/blink-182","name":"blink-182","@attr":{"rank":"6"},"playcount":"19"},{"mbid":"","url":"https://www.last.fm/music/Obliteration","name":"Obliteration","@attr":{"rank":"7"},"playcount":"19"},{"mbid":"e9452446-7702-4853-96ce-5dfe6748d3fb","url":"https://www.last.fm/music/Wolves+in+the+Throne+Room","name":"Wolves in the Throne Room","@attr":{"rank":"8"},"playcount":"14"},{"mbid":"68ff4824-8451-481c-b4cf-57c2c64d8c00","url":"https://www.last.fm/music/Knuckle+Puck","name":"Knuckle Puck","@attr":{"rank":"9"},"playcount":"11"},{"mbid":"546e82a3-550b-4cf2-8cb8-595d9d32aa49","url":"https://www.last.fm/music/Fleshwater","name":"Fleshwater","@attr":{"rank":"10"},"playcount":"10"},{"mbid":"0f3f7357-73d3-42a3-81a5-b359bc4e8a56","url":"https://www.last.fm/music/Portrayal+of+Guilt","name":"Portrayal of Guilt","@attr":{"rank":"11"},"playcount":"9"},{"mbid":"5bba23fa-23ad-4129-8a67-245d373be0ee","url":"https://www.last.fm/music/Fiddlehead","name":"Fiddlehead","@attr":{"rank":"12"},"playcount":"8"},{"mbid":"cc546218-cc08-4ae9-9592-ac1596c1470d","url":"https://www.last.fm/music/Propagandhi","name":"Propagandhi","@attr":{"rank":"13"},"playcount":"7"},{"mbid":"37e9d7b2-7779-41b2-b2eb-3685351caad3","url":"https://www.last.fm/music/NoMeansNo","name":"NoMeansNo","@attr":{"rank":"14"},"playcount":"6"},{"mbid":"d2c944b5-7475-47bd-b3bf-df1b68f80a68","url":"https://www.last.fm/music/Narrow+Head","name":"Narrow Head","@attr":{"rank":"15"},"playcount":"4"}],"@attr":{"from":"1704974400","user":"coryd_","to":"1705579200"}}},{"weeklyartistchart":{"artist":[{"mbid":"d4ad0149-d8ae-4105-8009-0221fce9ff35","url":"https://www.last.fm/music/Minutemen","name":"Minutemen","@attr":{"rank":"1"},"playcount":"79"},{"mbid":"7f2a8098-50e3-451c-8696-c5d9f64f4762","url":"https://www.last.fm/music/Wire","name":"Wire","@attr":{"rank":"2"},"playcount":"43"},{"mbid":"37e9d7b2-7779-41b2-b2eb-3685351caad3","url":"https://www.last.fm/music/NoMeansNo","name":"NoMeansNo","@attr":{"rank":"3"},"playcount":"30"},{"mbid":"4ef06a0d-b8d1-42b4-aff8-06f223306cdb","url":"https://www.last.fm/music/Cloud+Rat","name":"Cloud Rat","@attr":{"rank":"4"},"playcount":"29"},{"mbid":"07b251a1-7bdf-4955-a66c-88051bce9f0a","url":"https://www.last.fm/music/Dead+In+The+Dirt","name":"Dead In The Dirt","@attr":{"rank":"5"},"playcount":"25"},{"mbid":"5c9dd772-a38f-4873-baa8-4b5d9dff3990","url":"https://www.last.fm/music/Spanish+Love+Songs","name":"Spanish Love Songs","@attr":{"rank":"6"},"playcount":"24"},{"mbid":"","url":"https://www.last.fm/music/Soul+Blind","name":"Soul Blind","@attr":{"rank":"7"},"playcount":"22"},{"mbid":"143fd9a0-28a4-42fb-911e-e5c00baf06f9","url":"https://www.last.fm/music/Wormrot","name":"Wormrot","@attr":{"rank":"8"},"playcount":"19"},{"mbid":"664c3e0e-42d8-48c1-b209-1efca19c0325","url":"https://www.last.fm/music/The+National","name":"The National","@attr":{"rank":"9"},"playcount":"16"},{"mbid":"20839532-372b-41c9-8b22-04995bd21a49","url":"https://www.last.fm/music/Au-Dessus","name":"Au-Dessus","@attr":{"rank":"10"},"playcount":"6"},{"mbid":"37ea73dd-a48c-4659-8b9d-5c77bd9cbd12","url":"https://www.last.fm/music/Deathspell+Omega","name":"Deathspell Omega","@attr":{"rank":"11"},"playcount":"1"}],"@attr":{"from":"1705579200","user":"coryd_","to":"1706184000"}}},{"weeklyartistchart":{"artist":[{"mbid":"07b251a1-7bdf-4955-a66c-88051bce9f0a","url":"https://www.last.fm/music/Dead+In+The+Dirt","name":"Dead In The Dirt","@attr":{"rank":"1"},"playcount":"35"},{"mbid":"37e9d7b2-7779-41b2-b2eb-3685351caad3","url":"https://www.last.fm/music/NoMeansNo","name":"NoMeansNo","@attr":{"rank":"2"},"playcount":"30"},{"mbid":"","url":"https://www.last.fm/music/Autopsy","name":"Autopsy","@attr":{"rank":"3"},"playcount":"29"},{"mbid":"91cd46b7-30ef-4b99-a332-89512c02df2e","url":"https://www.last.fm/music/Fawn+Limbs","name":"Fawn Limbs","@attr":{"rank":"4"},"playcount":"23"},{"mbid":"3d5368fd-a9bf-4a58-ad37-a6f26c248d67","url":"https://www.last.fm/music/Resurgency","name":"Resurgency","@attr":{"rank":"5"},"playcount":"23"},{"mbid":"7bfc9a9a-ee6a-4a0a-8643-9d790c8d956f","url":"https://www.last.fm/music/Hyperdontia","name":"Hyperdontia","@attr":{"rank":"6"},"playcount":"22"},{"mbid":"17098248-792c-4396-b784-0ba0ed3314d0","url":"https://www.last.fm/music/Khthoniik+Cerviiks","name":"Khthoniik Cerviiks","@attr":{"rank":"7"},"playcount":"22"},{"mbid":"0743b15a-3c32-48c8-ad58-cb325350befa","url":"https://www.last.fm/music/blink-182","name":"blink-182","@attr":{"rank":"8"},"playcount":"19"},{"mbid":"78783494-b757-4d0b-9a74-12261a851e4c","url":"https://www.last.fm/music/Suffering+Hour","name":"Suffering Hour","@attr":{"rank":"9"},"playcount":"17"},{"mbid":"dd4d9439-87ee-455d-a8b3-a96364845233","url":"https://www.last.fm/music/Unaussprechlichen+Kulten","name":"Unaussprechlichen Kulten","@attr":{"rank":"10"},"playcount":"17"},{"mbid":"","url":"https://www.last.fm/music/Cruciamentum","name":"Cruciamentum","@attr":{"rank":"11"},"playcount":"15"},{"mbid":"1ca441fa-7cea-4f29-939b-06d8741f74c7","url":"https://www.last.fm/music/Free+Throw","name":"Free Throw","@attr":{"rank":"12"},"playcount":"14"},{"mbid":"","url":"https://www.last.fm/music/Augury","name":"Augury","@attr":{"rank":"13"},"playcount":"12"},{"mbid":"8b73aa11-530c-46cc-9c1f-793462431174","url":"https://www.last.fm/music/Sovereign","name":"Sovereign","@attr":{"rank":"14"},"playcount":"12"},{"mbid":"69421e11-e4c3-4854-951b-ceab4972e38e","url":"https://www.last.fm/music/Alkaline+Trio","name":"Alkaline Trio","@attr":{"rank":"15"},"playcount":"11"},{"mbid":"92bca3de-6315-4de5-a45a-7103a4f895a4","url":"https://www.last.fm/music/SlimeLord","name":"SlimeLord","@attr":{"rank":"16"},"playcount":"10"},{"mbid":"a449014f-de9a-43fa-b271-786b0af10926","url":"https://www.last.fm/music/Undeath","name":"Undeath","@attr":{"rank":"17"},"playcount":"10"},{"mbid":"d316fcf3-108c-4186-be62-809167acaa3c","url":"https://www.last.fm/music/Replicant","name":"Replicant","@attr":{"rank":"18"},"playcount":"9"},{"mbid":"7fcd488b-f3fc-40c8-a82c-c18317d72aae","url":"https://www.last.fm/music/Gutvoid","name":"Gutvoid","@attr":{"rank":"19"},"playcount":"8"},{"mbid":"274d698c-81c1-48f7-b848-c4ab0730f486","url":"https://www.last.fm/music/Cantique+L%C3%A9preux","name":"Cantique Lépreux","@attr":{"rank":"20"},"playcount":"7"},{"mbid":"12a9e259-f7cb-4fca-87b1-a6c5fd38c300","url":"https://www.last.fm/music/Hot+Mulligan","name":"Hot Mulligan","@attr":{"rank":"21"},"playcount":"7"},{"mbid":"07dbcf53-1b4b-4274-a158-8e3f6302d56e","url":"https://www.last.fm/music/Olhava","name":"Olhava","@attr":{"rank":"22"},"playcount":"7"},{"mbid":"561d854a-6a28-4aa7-8c99-323e6ce46c2a","url":"https://www.last.fm/music/Miles+Davis","name":"Miles Davis","@attr":{"rank":"23"},"playcount":"5"},{"mbid":"a521f1a8-a949-4dcf-ab33-94596cb02787","url":"https://www.last.fm/music/Militarie+Gun","name":"Militarie Gun","@attr":{"rank":"24"},"playcount":"5"},{"mbid":"","url":"https://www.last.fm/music/Nucleus","name":"Nucleus","@attr":{"rank":"25"},"playcount":"3"},{"mbid":"b1e23ada-a7eb-42d7-91ec-67a43bead43a","url":"https://www.last.fm/music/Hypocrisy","name":"Hypocrisy","@attr":{"rank":"26"},"playcount":"2"},{"mbid":"4f00bd65-db98-4f18-85ab-a3a6b8ad32a0","url":"https://www.last.fm/music/Panopticon","name":"Panopticon","@attr":{"rank":"27"},"playcount":"2"},{"mbid":"2ab92969-929d-4057-a625-117814f0465b","url":"https://www.last.fm/music/Coffin+Curse","name":"Coffin Curse","@attr":{"rank":"28"},"playcount":"1"}],"@attr":{"from":"1706184000","user":"coryd_","to":"1706788800"}}},{"weeklyartistchart":{"artist":[{"mbid":"0f3f7357-73d3-42a3-81a5-b359bc4e8a56","url":"https://www.last.fm/music/Portrayal+of+Guilt","name":"Portrayal of Guilt","@attr":{"rank":"1"},"playcount":"52"},{"mbid":"","url":"https://www.last.fm/music/AFI","name":"AFI","@attr":{"rank":"2"},"playcount":"37"},{"mbid":"","url":"https://www.last.fm/music/Nucleus","name":"Nucleus","@attr":{"rank":"3"},"playcount":"34"},{"mbid":"3cb2b7a7-53e6-4b0c-9143-16227fc5d1c3","url":"https://www.last.fm/music/Hauntologist","name":"Hauntologist","@attr":{"rank":"4"},"playcount":"32"},{"mbid":"47a9a488-a721-4d0e-88bc-2452701fb9c9","url":"https://www.last.fm/music/Defeated+Sanity","name":"Defeated Sanity","@attr":{"rank":"5"},"playcount":"30"},{"mbid":"37e9d7b2-7779-41b2-b2eb-3685351caad3","url":"https://www.last.fm/music/NoMeansNo","name":"NoMeansNo","@attr":{"rank":"6"},"playcount":"27"},{"mbid":"aba64937-3334-4c65-90a1-4e6b9d4d7ada","url":"https://www.last.fm/music/Aesop+Rock","name":"Aesop Rock","@attr":{"rank":"7"},"playcount":"26"},{"mbid":"7961aa2c-36d4-4601-a691-981b18143991","url":"https://www.last.fm/music/Galvanizer","name":"Galvanizer","@attr":{"rank":"8"},"playcount":"24"},{"mbid":"48cb1769-b1fe-4730-a088-d83be4dc01ef","url":"https://www.last.fm/music/Sepulcher","name":"Sepulcher","@attr":{"rank":"9"},"playcount":"24"},{"mbid":"6c3b93e1-d3e7-413c-b030-b6ddd918676f","url":"https://www.last.fm/music/Dissimulator","name":"Dissimulator","@attr":{"rank":"10"},"playcount":"23"},{"mbid":"c5119d8a-ffee-48bc-99c3-f323bdf16d82","url":"https://www.last.fm/music/Vektor","name":"Vektor","@attr":{"rank":"11"},"playcount":"19"},{"mbid":"c16dcdae-a651-42c1-aff8-edda0f463157","url":"https://www.last.fm/music/Soft+Kill","name":"Soft Kill","@attr":{"rank":"12"},"playcount":"16"},{"mbid":"583352d8-936c-44fd-a74c-f43154c7aad8","url":"https://www.last.fm/music/Vertebra+Atlantis","name":"Vertebra Atlantis","@attr":{"rank":"13"},"playcount":"16"},{"mbid":"e7b4c928-8c45-4ecf-9f08-da64fe5c2ddd","url":"https://www.last.fm/music/Mg%C5%82a","name":"Mgła","@attr":{"rank":"14"},"playcount":"15"},{"mbid":"28f69ba3-641c-4b6d-a38d-e60a444213fc","url":"https://www.last.fm/music/Last+Sacrament","name":"Last Sacrament","@attr":{"rank":"15"},"playcount":"14"},{"mbid":"dd4d9439-87ee-455d-a8b3-a96364845233","url":"https://www.last.fm/music/Unaussprechlichen+Kulten","name":"Unaussprechlichen Kulten","@attr":{"rank":"16"},"playcount":"12"},{"mbid":"4de7df66-b805-4183-87af-ac38477b624a","url":"https://www.last.fm/music/Frail+Body","name":"Frail Body","@attr":{"rank":"17"},"playcount":"10"},{"mbid":"a95ef44c-aeda-4222-9d57-10b28240e634","url":"https://www.last.fm/music/Gorguts","name":"Gorguts","@attr":{"rank":"18"},"playcount":"10"},{"mbid":"20839532-372b-41c9-8b22-04995bd21a49","url":"https://www.last.fm/music/Au-Dessus","name":"Au-Dessus","@attr":{"rank":"19"},"playcount":"8"},{"mbid":"7748c80b-c597-44c8-8c13-bb1ebfd62285","url":"https://www.last.fm/music/Exlimitir","name":"Exlimitir","@attr":{"rank":"20"},"playcount":"8"},{"mbid":"03f9e6f0-7c7f-4fd6-a47f-f0b0425f314b","url":"https://www.last.fm/music/Mis%C3%BEyrming","name":"Misþyrming","@attr":{"rank":"21"},"playcount":"4"},{"mbid":"1ca441fa-7cea-4f29-939b-06d8741f74c7","url":"https://www.last.fm/music/Free+Throw","name":"Free Throw","@attr":{"rank":"22"},"playcount":"3"}],"@attr":{"from":"1706788800","user":"coryd_","to":"1707393600"}}},{"weeklyartistchart":{"artist":[{"mbid":"9e86aeef-99ec-419e-9ce3-25d21bc5665f","url":"https://www.last.fm/music/Inculter","name":"Inculter","@attr":{"rank":"1"},"playcount":"32"},{"mbid":"","url":"https://www.last.fm/music/Contaminated","name":"Contaminated","@attr":{"rank":"2"},"playcount":"28"},{"mbid":"37ea73dd-a48c-4659-8b9d-5c77bd9cbd12","url":"https://www.last.fm/music/Deathspell+Omega","name":"Deathspell Omega","@attr":{"rank":"3"},"playcount":"28"},{"mbid":"","url":"https://www.last.fm/music/Augury","name":"Augury","@attr":{"rank":"4"},"playcount":"27"},{"mbid":"68ff4824-8451-481c-b4cf-57c2c64d8c00","url":"https://www.last.fm/music/Knuckle+Puck","name":"Knuckle Puck","@attr":{"rank":"5"},"playcount":"27"},{"mbid":"e7b4c928-8c45-4ecf-9f08-da64fe5c2ddd","url":"https://www.last.fm/music/Mg%C5%82a","name":"Mgła","@attr":{"rank":"6"},"playcount":"27"},{"mbid":"f4ccf6c5-ad41-4f8f-bb9e-6e2c6ad23302","url":"https://www.last.fm/music/Deafheaven","name":"Deafheaven","@attr":{"rank":"7"},"playcount":"26"},{"mbid":"0743b15a-3c32-48c8-ad58-cb325350befa","url":"https://www.last.fm/music/blink-182","name":"blink-182","@attr":{"rank":"8"},"playcount":"25"},{"mbid":"524a03b1-ceb7-4678-8aba-af87914f0c9e","url":"https://www.last.fm/music/Webbed+Wing","name":"Webbed Wing","@attr":{"rank":"9"},"playcount":"22"},{"mbid":"29616e0c-78d6-4c5f-99e2-d9e113d19d6a","url":"https://www.last.fm/music/Vircolac","name":"Vircolac","@attr":{"rank":"10"},"playcount":"20"},{"mbid":"1ca441fa-7cea-4f29-939b-06d8741f74c7","url":"https://www.last.fm/music/Free+Throw","name":"Free Throw","@attr":{"rank":"11"},"playcount":"18"},{"mbid":"4d2949b4-eb5f-4296-b71a-04603c6a9802","url":"https://www.last.fm/music/Rotten+Sound","name":"Rotten Sound","@attr":{"rank":"12"},"playcount":"18"},{"mbid":"f7579430-af4b-42e6-86c7-4c24a8411b58","url":"https://www.last.fm/music/CIVEROUS","name":"CIVEROUS","@attr":{"rank":"13"},"playcount":"14"},{"mbid":"27a3ffb1-b3c6-422f-88a0-463a497f2d6f","url":"https://www.last.fm/music/Chapel+of+Disease","name":"Chapel of Disease","@attr":{"rank":"14"},"playcount":"12"},{"mbid":"3cb2b7a7-53e6-4b0c-9143-16227fc5d1c3","url":"https://www.last.fm/music/Hauntologist","name":"Hauntologist","@attr":{"rank":"15"},"playcount":"8"},{"mbid":"0605f3df-fbc2-4dcd-8b98-804a9a4c66bd","url":"https://www.last.fm/music/Spectral+Voice","name":"Spectral Voice","@attr":{"rank":"16"},"playcount":"8"},{"mbid":"664c3e0e-42d8-48c1-b209-1efca19c0325","url":"https://www.last.fm/music/The+National","name":"The National","@attr":{"rank":"17"},"playcount":"6"},{"mbid":"4bc3810d-e872-41d9-8dc2-ca9ff4fbb7ba","url":"https://www.last.fm/music/Devoid+of+Thought","name":"Devoid of Thought","@attr":{"rank":"18"},"playcount":"5"}],"@attr":{"from":"1707393600","user":"coryd_","to":"1707998400"}}},{"weeklyartistchart":{"artist":[{"mbid":"d4ad0149-d8ae-4105-8009-0221fce9ff35","url":"https://www.last.fm/music/Minutemen","name":"Minutemen","@attr":{"rank":"1"},"playcount":"43"},{"mbid":"864aa861-e22a-4187-8baa-2ef0c215bc0a","url":"https://www.last.fm/music/Godflesh","name":"Godflesh","@attr":{"rank":"2"},"playcount":"38"},{"mbid":"2de34daa-7256-495f-84c2-9f7459748492","url":"https://www.last.fm/music/Hooded+Menace","name":"Hooded Menace","@attr":{"rank":"3"},"playcount":"36"},{"mbid":"c3aeb863-7b26-4388-94e8-5a240f2be21b","url":"https://www.last.fm/music/Tom+Waits","name":"Tom Waits","@attr":{"rank":"4"},"playcount":"35"},{"mbid":"f6e61750-a6b7-4d88-979b-052345cd0e4a","url":"https://www.last.fm/music/Sturgill+Simpson","name":"Sturgill Simpson","@attr":{"rank":"5"},"playcount":"32"},{"mbid":"c00a4a56-4289-47bb-a852-758ffb6171ad","url":"https://www.last.fm/music/+noredirect/Rotted","name":"Rotted","@attr":{"rank":"6"},"playcount":"28"},{"mbid":"","url":"https://www.last.fm/music/AFI","name":"AFI","@attr":{"rank":"7"},"playcount":"27"},{"mbid":"d2c944b5-7475-47bd-b3bf-df1b68f80a68","url":"https://www.last.fm/music/Narrow+Head","name":"Narrow Head","@attr":{"rank":"8"},"playcount":"26"},{"mbid":"7961aa2c-36d4-4601-a691-981b18143991","url":"https://www.last.fm/music/Galvanizer","name":"Galvanizer","@attr":{"rank":"9"},"playcount":"24"},{"mbid":"4d2949b4-eb5f-4296-b71a-04603c6a9802","url":"https://www.last.fm/music/Rotten+Sound","name":"Rotten Sound","@attr":{"rank":"10"},"playcount":"22"},{"mbid":"dc0d05ce-2f47-4962-b4fa-8631a0a51987","url":"https://www.last.fm/music/The+Replacements","name":"The Replacements","@attr":{"rank":"11"},"playcount":"22"},{"mbid":"5b67060c-6ec8-4ee8-9783-2207c169402d","url":"https://www.last.fm/music/Svartidau%C3%B0i","name":"Svartidauði","@attr":{"rank":"12"},"playcount":"19"},{"mbid":"12a9e259-f7cb-4fca-87b1-a6c5fd38c300","url":"https://www.last.fm/music/Hot+Mulligan","name":"Hot Mulligan","@attr":{"rank":"13"},"playcount":"13"},{"mbid":"","url":"https://www.last.fm/music/Sunday+Valley","name":"Sunday Valley","@attr":{"rank":"14"},"playcount":"10"},{"mbid":"d39ffe1a-ef5d-4f01-8a14-8f7195b4ce86","url":"https://www.last.fm/music/Dead+Bob","name":"Dead Bob","@attr":{"rank":"15"},"playcount":"7"},{"mbid":"5c9dd772-a38f-4873-baa8-4b5d9dff3990","url":"https://www.last.fm/music/Spanish+Love+Songs","name":"Spanish Love Songs","@attr":{"rank":"16"},"playcount":"7"},{"mbid":"","url":"https://www.last.fm/music/Contaminated","name":"Contaminated","@attr":{"rank":"17"},"playcount":"6"},{"mbid":"546e82a3-550b-4cf2-8cb8-595d9d32aa49","url":"https://www.last.fm/music/Fleshwater","name":"Fleshwater","@attr":{"rank":"18"},"playcount":"5"},{"mbid":"233fc3f3-6de2-465c-985e-e721dbabbace","url":"https://www.last.fm/music/Fugazi","name":"Fugazi","@attr":{"rank":"19"},"playcount":"3"},{"mbid":"d347406f-839d-4423-9a28-188939282afa","url":"https://www.last.fm/music/Cult+of+Luna","name":"Cult of Luna","@attr":{"rank":"20"},"playcount":"2"},{"mbid":"","url":"https://www.last.fm/music/home+is+where","name":"home is where","@attr":{"rank":"21"},"playcount":"2"},{"mbid":"2aab61bc-67f4-4722-8c6e-e1821b2e32a6","url":"https://www.last.fm/music/Violent+Femmes","name":"Violent Femmes","@attr":{"rank":"22"},"playcount":"2"},{"mbid":"82315599-2215-4c3e-a36f-87be58d06ec0","url":"https://www.last.fm/music/J+Mascis","name":"J Mascis","@attr":{"rank":"23"},"playcount":"1"}],"@attr":{"from":"1707998400","user":"coryd_","to":"1708603200"}}},{"weeklyartistchart":{"artist":[{"mbid":"","url":"https://www.last.fm/music/Death","name":"Death","@attr":{"rank":"1"},"playcount":"51"},{"mbid":"29616e0c-78d6-4c5f-99e2-d9e113d19d6a","url":"https://www.last.fm/music/Vircolac","name":"Vircolac","@attr":{"rank":"2"},"playcount":"45"},{"mbid":"945d3b69-27cd-45fa-b491-52553a63dead","url":"https://www.last.fm/music/Joyce+Manor","name":"Joyce Manor","@attr":{"rank":"3"},"playcount":"39"},{"mbid":"552cd2a3-ac51-464d-8222-dcdbb08a8d2d","url":"https://www.last.fm/music/Tomb+Mold","name":"Tomb Mold","@attr":{"rank":"4"},"playcount":"34"},{"mbid":"68bd8072-0412-44b1-81dd-807aa6c1918c","url":"https://www.last.fm/music/Bolt+Thrower","name":"Bolt Thrower","@attr":{"rank":"5"},"playcount":"33"},{"mbid":"","url":"https://www.last.fm/music/Contaminated","name":"Contaminated","@attr":{"rank":"6"},"playcount":"30"},{"mbid":"49c15d5f-469e-469c-ae94-89e8d31106dd","url":"https://www.last.fm/music/Dismember","name":"Dismember","@attr":{"rank":"7"},"playcount":"29"},{"mbid":"c837c0fa-74dd-483b-95f7-25a46f92fa88","url":"https://www.last.fm/music/Prince+Daddy+&+The+Hyena","name":"Prince Daddy & The Hyena","@attr":{"rank":"8"},"playcount":"27"},{"mbid":"","url":"https://www.last.fm/music/Cruciamentum","name":"Cruciamentum","@attr":{"rank":"9"},"playcount":"21"},{"mbid":"eb96a85e-4ac0-49a1-ad42-24becfa1a125","url":"https://www.last.fm/music/Grave+Infestation","name":"Grave Infestation","@attr":{"rank":"10"},"playcount":"20"},{"mbid":"4bc3810d-e872-41d9-8dc2-ca9ff4fbb7ba","url":"https://www.last.fm/music/Devoid+of+Thought","name":"Devoid of Thought","@attr":{"rank":"11"},"playcount":"18"},{"mbid":"7fcd488b-f3fc-40c8-a82c-c18317d72aae","url":"https://www.last.fm/music/Gutvoid","name":"Gutvoid","@attr":{"rank":"12"},"playcount":"18"},{"mbid":"a5f0f298-776a-4909-bc09-4fd56a680542","url":"https://www.last.fm/music/Blood+Incantation","name":"Blood Incantation","@attr":{"rank":"13"},"playcount":"16"},{"mbid":"583352d8-936c-44fd-a74c-f43154c7aad8","url":"https://www.last.fm/music/Vertebra+Atlantis","name":"Vertebra Atlantis","@attr":{"rank":"14"},"playcount":"14"},{"mbid":"668d51a7-8b9c-4392-959a-2f1cfdf08e02","url":"https://www.last.fm/music/Demigod","name":"Demigod","@attr":{"rank":"15"},"playcount":"12"},{"mbid":"053c3c45-559a-4af7-adee-6cf3c7dd82c1","url":"https://www.last.fm/music/Sincere+Engineer","name":"Sincere Engineer","@attr":{"rank":"16"},"playcount":"11"},{"mbid":"0fe0a2ed-b891-4d73-ad87-05f4efbdddcd","url":"https://www.last.fm/music/Bedsore","name":"Bedsore","@attr":{"rank":"17"},"playcount":"10"},{"mbid":"82315599-2215-4c3e-a36f-87be58d06ec0","url":"https://www.last.fm/music/J+Mascis","name":"J Mascis","@attr":{"rank":"18"},"playcount":"9"},{"mbid":"ec88cdc3-0517-4951-b5ef-7323e7316db0","url":"https://www.last.fm/music/Jawbreaker","name":"Jawbreaker","@attr":{"rank":"19"},"playcount":"9"},{"mbid":"d39ffe1a-ef5d-4f01-8a14-8f7195b4ce86","url":"https://www.last.fm/music/Dead+Bob","name":"Dead Bob","@attr":{"rank":"20"},"playcount":"4"},{"mbid":"cc546218-cc08-4ae9-9592-ac1596c1470d","url":"https://www.last.fm/music/Propagandhi","name":"Propagandhi","@attr":{"rank":"21"},"playcount":"4"},{"mbid":"a50f2124-e056-4c57-bd4e-d23a9a94df82","url":"https://www.last.fm/music/State+Lines","name":"State Lines","@attr":{"rank":"22"},"playcount":"4"},{"mbid":"1b54e90c-638e-4fdd-a20e-4ab09db9fdaf","url":"https://www.last.fm/music/The+Get+Up+Kids","name":"The Get Up Kids","@attr":{"rank":"23"},"playcount":"4"},{"mbid":"f7579430-af4b-42e6-86c7-4c24a8411b58","url":"https://www.last.fm/music/CIVEROUS","name":"CIVEROUS","@attr":{"rank":"24"},"playcount":"3"},{"mbid":"","url":"https://www.last.fm/music/Envy","name":"Envy","@attr":{"rank":"25"},"playcount":"3"},{"mbid":"69228a53-5c21-421d-ad9d-c085c6bde556","url":"https://www.last.fm/music/Gutter+Instinct","name":"Gutter Instinct","@attr":{"rank":"26"},"playcount":"3"},{"mbid":"e7b4c928-8c45-4ecf-9f08-da64fe5c2ddd","url":"https://www.last.fm/music/Mg%C5%82a","name":"Mgła","@attr":{"rank":"27"},"playcount":"1"},{"mbid":"0acc305d-e58b-4e76-bc17-630345c14b38","url":"https://www.last.fm/music/Michael+Cera+Palin","name":"Michael Cera Palin","@attr":{"rank":"28"},"playcount":"1"}],"@attr":{"from":"1708603200","user":"coryd_","to":"1709208000"}}},{"weeklyartistchart":{"artist":[{"mbid":"cd956e47-4b34-4a3d-b053-1d8dc5a36f49","url":"https://www.last.fm/music/Execration","name":"Execration","@attr":{"rank":"1"},"playcount":"44"},{"mbid":"d50a4b89-ff1f-4659-9fde-f76f8d5b3c89","url":"https://www.last.fm/music/Carcass","name":"Carcass","@attr":{"rank":"2"},"playcount":"43"},{"mbid":"68bd8072-0412-44b1-81dd-807aa6c1918c","url":"https://www.last.fm/music/Bolt+Thrower","name":"Bolt Thrower","@attr":{"rank":"3"},"playcount":"38"},{"mbid":"92bca3de-6315-4de5-a45a-7103a4f895a4","url":"https://www.last.fm/music/SlimeLord","name":"SlimeLord","@attr":{"rank":"4"},"playcount":"35"},{"mbid":"3cb2b7a7-53e6-4b0c-9143-16227fc5d1c3","url":"https://www.last.fm/music/Hauntologist","name":"Hauntologist","@attr":{"rank":"5"},"playcount":"32"},{"mbid":"","url":"https://www.last.fm/music/Rapture","name":"Rapture","@attr":{"rank":"6"},"playcount":"29"},{"mbid":"2c560b38-d7a9-4b2a-9ee3-e183b9549248","url":"https://www.last.fm/music/White+Ward","name":"White Ward","@attr":{"rank":"7"},"playcount":"27"},{"mbid":"49c15d5f-469e-469c-ae94-89e8d31106dd","url":"https://www.last.fm/music/Dismember","name":"Dismember","@attr":{"rank":"8"},"playcount":"25"},{"mbid":"552cd2a3-ac51-464d-8222-dcdbb08a8d2d","url":"https://www.last.fm/music/Tomb+Mold","name":"Tomb Mold","@attr":{"rank":"9"},"playcount":"24"},{"mbid":"1ca441fa-7cea-4f29-939b-06d8741f74c7","url":"https://www.last.fm/music/Free+Throw","name":"Free Throw","@attr":{"rank":"10"},"playcount":"23"},{"mbid":"4f00bd65-db98-4f18-85ab-a3a6b8ad32a0","url":"https://www.last.fm/music/Panopticon","name":"Panopticon","@attr":{"rank":"11"},"playcount":"17"},{"mbid":"","url":"https://www.last.fm/music/Shards+of+Humanity","name":"Shards of Humanity","@attr":{"rank":"12"},"playcount":"17"},{"mbid":"5c9dd772-a38f-4873-baa8-4b5d9dff3990","url":"https://www.last.fm/music/Spanish+Love+Songs","name":"Spanish Love Songs","@attr":{"rank":"13"},"playcount":"9"},{"mbid":"","url":"https://www.last.fm/music/Contaminated","name":"Contaminated","@attr":{"rank":"14"},"playcount":"7"},{"mbid":"1bb3087a-0257-46f1-b693-ad99ffe495b2","url":"https://www.last.fm/music/Krypts","name":"Krypts","@attr":{"rank":"15"},"playcount":"7"},{"mbid":"37e9d7b2-7779-41b2-b2eb-3685351caad3","url":"https://www.last.fm/music/NoMeansNo","name":"NoMeansNo","@attr":{"rank":"16"},"playcount":"7"},{"mbid":"dd4d9439-87ee-455d-a8b3-a96364845233","url":"https://www.last.fm/music/Unaussprechlichen+Kulten","name":"Unaussprechlichen Kulten","@attr":{"rank":"17"},"playcount":"7"},{"mbid":"80d1c674-01a3-4b34-b3d5-b511aa6b277a","url":"https://www.last.fm/music/Skeletal+Remains","name":"Skeletal Remains","@attr":{"rank":"18"},"playcount":"5"},{"mbid":"82315599-2215-4c3e-a36f-87be58d06ec0","url":"https://www.last.fm/music/J+Mascis","name":"J Mascis","@attr":{"rank":"19"},"playcount":"2"},{"mbid":"77c167d2-4965-4421-830a-9815e4956475","url":"https://www.last.fm/music/Dinosaur+Jr.","name":"Dinosaur Jr.","@attr":{"rank":"20"},"playcount":"1"},{"mbid":"5bba23fa-23ad-4129-8a67-245d373be0ee","url":"https://www.last.fm/music/Fiddlehead","name":"Fiddlehead","@attr":{"rank":"21"},"playcount":"1"},{"mbid":"7961aa2c-36d4-4601-a691-981b18143991","url":"https://www.last.fm/music/Galvanizer","name":"Galvanizer","@attr":{"rank":"22"},"playcount":"1"},{"mbid":"0605f3df-fbc2-4dcd-8b98-804a9a4c66bd","url":"https://www.last.fm/music/Spectral+Voice","name":"Spectral Voice","@attr":{"rank":"23"},"playcount":"1"}],"@attr":{"from":"1709208000","user":"coryd_","to":"1709812800"}}},{"weeklyartistchart":{"artist":[{"mbid":"d50a4b89-ff1f-4659-9fde-f76f8d5b3c89","url":"https://www.last.fm/music/Carcass","name":"Carcass","@attr":{"rank":"1"},"playcount":"59"},{"mbid":"","url":"https://www.last.fm/music/AFI","name":"AFI","@attr":{"rank":"2"},"playcount":"51"},{"mbid":"37e9d7b2-7779-41b2-b2eb-3685351caad3","url":"https://www.last.fm/music/NoMeansNo","name":"NoMeansNo","@attr":{"rank":"3"},"playcount":"46"},{"mbid":"8a336d3c-d767-4803-88b5-1a95823bef64","url":"https://www.last.fm/music/Convulsing","name":"Convulsing","@attr":{"rank":"4"},"playcount":"45"},{"mbid":"ce38e067-8e83-4660-8852-0c1db7ddaadb","url":"https://www.last.fm/music/Edge+of+Sanity","name":"Edge of Sanity","@attr":{"rank":"5"},"playcount":"44"},{"mbid":"","url":"https://www.last.fm/music/Autopsy","name":"Autopsy","@attr":{"rank":"6"},"playcount":"42"},{"mbid":"cc546218-cc08-4ae9-9592-ac1596c1470d","url":"https://www.last.fm/music/Propagandhi","name":"Propagandhi","@attr":{"rank":"7"},"playcount":"39"},{"mbid":"552cd2a3-ac51-464d-8222-dcdbb08a8d2d","url":"https://www.last.fm/music/Tomb+Mold","name":"Tomb Mold","@attr":{"rank":"8"},"playcount":"34"},{"mbid":"4f00bd65-db98-4f18-85ab-a3a6b8ad32a0","url":"https://www.last.fm/music/Panopticon","name":"Panopticon","@attr":{"rank":"9"},"playcount":"33"},{"mbid":"80d1c674-01a3-4b34-b3d5-b511aa6b277a","url":"https://www.last.fm/music/Skeletal+Remains","name":"Skeletal Remains","@attr":{"rank":"10"},"playcount":"30"},{"mbid":"32d2897c-4c91-46db-8161-f51d3f4f0d93","url":"https://www.last.fm/music/Drug+Church","name":"Drug Church","@attr":{"rank":"11"},"playcount":"25"},{"mbid":"4d2949b4-eb5f-4296-b71a-04603c6a9802","url":"https://www.last.fm/music/Rotten+Sound","name":"Rotten Sound","@attr":{"rank":"12"},"playcount":"16"},{"mbid":"64d475ac-2678-4535-b220-009a098a5b44","url":"https://www.last.fm/music/Worm","name":"Worm","@attr":{"rank":"13"},"playcount":"16"},{"mbid":"9efaf639-6332-44b8-94ae-c25896320ca7","url":"https://www.last.fm/music/Protomartyr","name":"Protomartyr","@attr":{"rank":"14"},"playcount":"4"},{"mbid":"","url":"https://www.last.fm/music/Fen","name":"Fen","@attr":{"rank":"15"},"playcount":"3"},{"mbid":"7f2a8098-50e3-451c-8696-c5d9f64f4762","url":"https://www.last.fm/music/Wire","name":"Wire","@attr":{"rank":"16"},"playcount":"3"},{"mbid":"c14b4180-dc87-481e-b17a-64e4150f90f6","url":"https://www.last.fm/music/Opeth","name":"Opeth","@attr":{"rank":"17"},"playcount":"2"},{"mbid":"26eaa84f-25e4-4311-b5d6-d184d146c7c0","url":"https://www.last.fm/music/Gorephilia","name":"Gorephilia","@attr":{"rank":"18"},"playcount":"1"},{"mbid":"d4ad0149-d8ae-4105-8009-0221fce9ff35","url":"https://www.last.fm/music/Minutemen","name":"Minutemen","@attr":{"rank":"19"},"playcount":"1"}],"@attr":{"from":"1709812800","user":"coryd_","to":"1710417600"}}}]}
